{"patents":[{"pat":"4128658","n_claims":4,"claims":[{"id":"4128658_c1","text":"42. A method of treating a condition mediated through histamine H 2 -receptors which comprises administering to a patient an effective amount of a compound as claimed in claim 1 to relieve said condit..."},{"id":"4128658_c2","text":"42. A method of treating a condition mediated through histamine H 2 -receptors which comprises administering to a patient an effective amount of a compound as claimed in claim 1 to relieve said condit..."},{"id":"4128658_c3","text":"42. A method of treating a condition mediated through histamine H 2 -receptors which comprises administering to a patient an effective amount of a compound as claimed in claim 1 to relieve said condit..."}]},{"pat":"4521431","n_claims":7,"claims":[{"id":"4521431_c1","text":"17. A method of treating condition mediated through histamine H 2 -receptors which comprises administering to a patient an effective amount of a compound as claimed in claim 1 to relieve said conditio..."},{"id":"4521431_c2","text":"17. A method of treating condition mediated through histamine H 2 -receptors which comprises administering to a patient an effective amount of a compound as claimed in claim 1 to relieve said conditio..."},{"id":"4521431_c3","text":"17. A method of treating condition mediated through histamine H 2 -receptors which comprises administering to a patient an effective amount of a compound as claimed in claim 1 to relieve said conditio..."},{"id":"4521431_c4","text":"18. A method of treating condition mediated through histamine H 2 -receptors which comprises administering to a patient an effective amount of a compound as claimed in claim 2 to relieve said conditio..."},{"id":"4521431_c5","text":"18. A method of treating condition mediated through histamine H 2 -receptors which comprises administering to a patient an effective amount of a compound as claimed in claim 2 to relieve said conditio..."},{"id":"4521431_c6","text":"18. A method of treating condition mediated through histamine H 2 -receptors which comprises administering to a patient an effective amount of a compound as claimed in claim 2 to relieve said conditio..."}]},{"pat":"4585790","n_claims":1,"claims":[{"id":"4585790_c0","text":"We claim: 1. A pharmaceutical composition which is an aqueous formulation containing an effective amount of ranitidine and/or one or more physiologically acceptable salts thereof for treatment of cond..."}]}],"use_codes":[{"code":"U-121","desc":"METHOD OF TREATING CONDITIONS MEDIATED THROUGH HISTAMINE H2-RECEPTORS","iu":0.9002,"ug":0.0563}],"edges":[{"c":"4128658_c1","u":"U-121","s":0.9489,"g":0.0487},{"c":"4128658_c2","u":"U-121","s":0.9489,"g":0.0487},{"c":"4128658_c3","u":"U-121","s":0.9489,"g":0.0487},{"c":"4521431_c1","u":"U-121","s":0.9552,"g":0.055},{"c":"4521431_c2","u":"U-121","s":0.9552,"g":0.055},{"c":"4521431_c3","u":"U-121","s":0.9552,"g":0.055},{"c":"4521431_c4","u":"U-121","s":0.9565,"g":0.0563},{"c":"4521431_c5","u":"U-121","s":0.9565,"g":0.0563},{"c":"4521431_c6","u":"U-121","s":0.9565,"g":0.0563},{"c":"4585790_c0","u":"U-121","s":0.8864,"g":-0.0138}],"uc_years":{"U-121":[1997,1998,1999,2000,2001,2002]},"pat_ucs":{"4128658":["U-121"],"4521431":["U-121"],"4585790":["U-121"]},"nda_gap":0.0563}