{"patents":[{"pat":"6031007","n_claims":4,"claims":[{"id":"6031007_c0","text":"We claim: 1. The pharmaceutical composition comprising: (i) one or more local anaesthetics in oil form; (ii) one or more surfactants in an amount effective to produce a homogenous formulation wherein,..."},{"id":"6031007_c1","text":"13. The method of treating a patient for pain associated with periodontal scaling, comprising applying to the periodontal pocket of said patient an effective amount of the pharmaceutical composition a..."},{"id":"6031007_c2","text":"13. The method of treating a patient for pain associated with periodontal scaling, comprising applying to the periodontal pocket of said patient an effective amount of the pharmaceutical composition a..."},{"id":"6031007_c3","text":"13. The method of treating a patient for pain associated with periodontal scaling, comprising applying to the periodontal pocket of said patient an effective amount of the pharmaceutical composition a..."}]}],"use_codes":[{"code":"U-553","desc":"MANAGEMENT OF PAIN AND DISCOMFORT ASSOCIATED WITH PERIDONTAL SCALING AND ROOT PLANNING PROCEDURES BY APPLICATION OF AN EUTECTIC MIXTURE OF LOCAL ANESTHETICS TO PERIDONTAL POCKETS","iu":0.9307,"ug":0.0127}],"edges":[{"c":"6031007_c0","u":"U-553","s":0.9125,"g":-0.0182},{"c":"6031007_c1","u":"U-553","s":0.9434,"g":0.0127},{"c":"6031007_c2","u":"U-553","s":0.9434,"g":0.0127},{"c":"6031007_c3","u":"U-553","s":0.9434,"g":0.0127}],"uc_years":{"U-553":[2005,2006,2007,2008,2009,2010,2011,2012,2013,2014,2015,2016,2017]},"pat_ucs":{"6031007":["U-553"]},"nda_gap":0.0127,"ci_claims":[{"c":"6031007_c0","ci":0.9254,"orphan":false},{"c":"6031007_c1","ci":0.9196,"orphan":false},{"c":"6031007_c2","ci":0.9196,"orphan":false},{"c":"6031007_c3","ci":0.9196,"orphan":false}],"ci_mean":0.9211,"orphan_rate":0.0,"indications":[{"id":"021451_20100927","date":"20100927","text":"Oraqix\u00ae is indicated for adults who require localized anesthesia in periodontal pockets during scaling\nand/or root planing.\nThis label may not be the latest approved by FDA.\nFor current labeling information, please visit https://www.fda.gov/drugsatfda"},{"id":"021451_20100419","date":"20100419","text":"for Use:\nThe Oraqix\u2122 Dispenser is indicated for the administration of ORAQIX (lidocaine and prilocaine periodontal gel) 2.5%/2.5%.\nContraindications:\nThis Dispenser is contraindicated for use with all injectable local anesthetic products.\nWarnings: \ufffd\nDO NOT INJECT Oraqix\u00ae (lidocaine and prilocaine p..."},{"id":"021451_20181105","date":"20181105","text":"2 DOSAGE AND ADMINISTRATION\n2.1 General Dosing Information\n2.2 Maximum Recommended Dosage\n3 DOSAGE FORMS AND STRENGTHS 4"},{"id":"021451_20031229","date":"20031229","text":"Oraqix is indicated for adults who require localized anesthesia in periodontal pockets during scaling\nand/or root planing.\nThis label may not be the latest approved by FDA.\nFor current labeling information, please visit https://www.fda.gov/drugsatfda\nNDA 21-451\nPage 9"},{"id":"021451_20120809","date":"20120809","text":"Oraqix is an amide local anesthetic indicated for adults who require localized anesthesia in periodontal pockets during\nscaling and/or root planing."}],"ci_edges":[{"c":"6031007_c0","i":"021451_20100927","s":0.9061},{"c":"6031007_c0","i":"021451_20100419","s":0.9254},{"c":"6031007_c0","i":"021451_20181105","s":0.9148},{"c":"6031007_c0","i":"021451_20031229","s":0.9059},{"c":"6031007_c0","i":"021451_20120809","s":0.9049},{"c":"6031007_c1","i":"021451_20100927","s":0.9196},{"c":"6031007_c1","i":"021451_20100419","s":0.9115},{"c":"6031007_c1","i":"021451_20181105","s":0.8929},{"c":"6031007_c1","i":"021451_20031229","s":0.9183},{"c":"6031007_c1","i":"021451_20120809","s":0.9194},{"c":"6031007_c2","i":"021451_20100927","s":0.9196},{"c":"6031007_c2","i":"021451_20100419","s":0.9115},{"c":"6031007_c2","i":"021451_20181105","s":0.8929},{"c":"6031007_c2","i":"021451_20031229","s":0.9183},{"c":"6031007_c2","i":"021451_20120809","s":0.9194},{"c":"6031007_c3","i":"021451_20100927","s":0.9196},{"c":"6031007_c3","i":"021451_20100419","s":0.9115},{"c":"6031007_c3","i":"021451_20181105","s":0.8929},{"c":"6031007_c3","i":"021451_20031229","s":0.9183},{"c":"6031007_c3","i":"021451_20120809","s":0.9194}]}