{"patents":[{"pat":"8791097","n_claims":7,"claims":[{"id":"8791097_c0","text":"The invention claimed is: 1. A method of treating papillary renal cell carcinoma in a mammal in need thereof, which comprises providing to said mammal an effective amount of CCI-779, wherein said papi..."},{"id":"8791097_c1","text":"1. A method of treating papillary renal cell carcinoma in a mammal in need thereof, which comprises providing to said mammal an effective amount of CCI-779, wherein said papillary renal cell carcinoma..."},{"id":"8791097_c2","text":"1. A method of treating papillary renal cell carcinoma in a mammal in need thereof, which comprises providing to said mammal an effective amount of CCI-779, wherein said papillary renal cell carcinoma..."},{"id":"8791097_c3","text":"1. A method of treating papillary renal cell carcinoma in a mammal in need thereof, which comprises providing to said mammal an effective amount of CCI-779, wherein said papillary renal cell carcinoma..."},{"id":"8791097_c4","text":"14. A method of treating papillary renal cell carcinoma in a mammal in need thereof, which comprises providing to said mammal an effective amount of CCI-779 in the absence of interferon alpha."},{"id":"8791097_c5","text":"14. A method of treating papillary renal cell carcinoma in a mammal in need thereof, which comprises providing to said mammal an effective amount of CCI-779 in the absence of interferon alpha."},{"id":"8791097_c6","text":"14. A method of treating papillary renal cell carcinoma in a mammal in need thereof, which comprises providing to said mammal an effective amount of CCI-779 in the absence of interferon alpha."}]}],"use_codes":[{"code":"U-1550","desc":"METHOD OF TREATING METASTATIC PAPILLARY RENAL CELL CARCINOMA WITH TEMSIROLIMUS.","iu":0.9264,"ug":0.0201},{"code":"U-1551","desc":"METHOD OF TREATING PAPILLARY RENAL CELL CARCINOMA WITH TEMSIROLIMUS, IN THE ABSENCE OF INTERFERON ALPHA.","iu":0.9261,"ug":0.0291}],"edges":[{"c":"8791097_c0","u":"U-1550","s":0.9274,"g":0.001},{"c":"8791097_c1","u":"U-1550","s":0.9465,"g":0.0201},{"c":"8791097_c2","u":"U-1550","s":0.9465,"g":0.0201},{"c":"8791097_c3","u":"U-1550","s":0.9465,"g":0.0201},{"c":"8791097_c4","u":"U-1550","s":0.9333,"g":0.0069},{"c":"8791097_c5","u":"U-1550","s":0.9333,"g":0.0069},{"c":"8791097_c6","u":"U-1550","s":0.9333,"g":0.0069},{"c":"8791097_c0","u":"U-1551","s":0.9363,"g":0.0102},{"c":"8791097_c1","u":"U-1551","s":0.9404,"g":0.0143},{"c":"8791097_c2","u":"U-1551","s":0.9404,"g":0.0143},{"c":"8791097_c3","u":"U-1551","s":0.9404,"g":0.0143},{"c":"8791097_c4","u":"U-1551","s":0.9552,"g":0.0291},{"c":"8791097_c5","u":"U-1551","s":0.9552,"g":0.0291},{"c":"8791097_c6","u":"U-1551","s":0.9552,"g":0.0291}],"uc_years":{"U-1550":[2015,2016,2017,2018,2019,2020,2021,2022,2023,2024],"U-1551":[2015,2016,2017,2018,2019,2020,2021,2022,2023,2024]},"pat_ucs":{"8791097":["U-1550","U-1551"]},"nda_gap":0.0246}