{"patents":[{"pat":"5677331","n_claims":4,"claims":[{"id":"5677331_c0","text":"We claim: 1. A pharmaceutical composition to be administered orally to humans, suitable for synergistic action of the combined active components against malaria, which composition consists of a synerg..."},{"id":"5677331_c1","text":"5. A method of treating malaria which comprises administering orally to a human in need of such treatment a synergistic antimalarially effective amount of a combination of benflumetol of formula (I) a..."},{"id":"5677331_c2","text":"5. A method of treating malaria which comprises administering orally to a human in need of such treatment a synergistic antimalarially effective amount of a combination of benflumetol of formula (I) a..."},{"id":"5677331_c3","text":"5. A method of treating malaria which comprises administering orally to a human in need of such treatment a synergistic antimalarially effective amount of a combination of benflumetol of formula (I) a..."}]}],"use_codes":[{"code":"U-977","desc":"TREATMENT OF ACUTE, UNCOMPLICATED MALARIA INFECTION DUE TO PLASMODIUM FALCIPARUM IN PATIENTS OF 5KG BODYWEIGHT AND ABOVE","iu":0.8912,"ug":0.0582}],"edges":[{"c":"5677331_c0","u":"U-977","s":0.919,"g":0.0278},{"c":"5677331_c1","u":"U-977","s":0.9494,"g":0.0582},{"c":"5677331_c2","u":"U-977","s":0.9494,"g":0.0582},{"c":"5677331_c3","u":"U-977","s":0.9494,"g":0.0582}],"uc_years":{"U-977":[2010,2011,2012,2013,2014,2015]},"pat_ucs":{"5677331":["U-977"]},"nda_gap":0.0582,"ci_claims":[{"c":"5677331_c0","ci":0.9288,"orphan":false},{"c":"5677331_c1","ci":0.9419,"orphan":false},{"c":"5677331_c2","ci":0.9419,"orphan":false},{"c":"5677331_c3","ci":0.9419,"orphan":false}],"ci_mean":0.9387,"orphan_rate":0.0,"indications":[{"id":"022268_20180109","date":"20180109","text":"7\n7\n.\n.\n7\n8\nS\nIn\ne\nt\nq\ne\nu\nra\ne\nc\nn\nt\nt\ni\ni\no\na\nn\nl U\nw\ns\nit\ne\nh\no\nD\nf\nr\nQ\nu\nu\ng\ni\ns\nn\nt\ni\nh\nn\na\ne\nt are Known to Prolong the QT Interval\n2 D\n2\n2\n2\n2\n.\n.\n.\n.\nO\n1\n2\n3\n4\nSAG\nA\nD\nD\nD\nd\no\no\no\nE\nm\ns\ns\ns\na\na\na\nA\ni\ng\ng\ng\nn\nN\ne\ne\ne\ni s\nD\ni\ni\ni\nt\nn\nn\nn\nr a\nA\nA\nP\nP\nti\nD\ne\na\nd\no\nd\nt\nu\nM\nn\ni\ni\ne\nl\na\nt\nn\nI\nI\nt\nn..."},{"id":"022268_20190806","date":"20190806","text":"Coartem Tablets are indicated for treatment of acute, uncomplicated malaria infections due to Plasmodium\nfalciparum in patients 2 months of age and older with a bodyweight of 5 kg and above. Coartem Tablets have\nbeen shown to be effective in geographical regions where resistance to chloroquine has b..."},{"id":"022268_20120807","date":"20120807","text":"7.5 Hormonal Contraceptives"},{"id":"022268_20100223","date":"20100223","text":"7.5 Sequential Use of Quinine"},{"id":"022268_20090416","date":"20090416","text":"8 USE IN SPECIFIC POPULATIONS"},{"id":"022268_20150320","date":"20150320","text":"7.6 CYP2D6 Substrates"},{"id":"022268_20130501","date":"20130501","text":"7.6 CYP2D6 Substrates"}],"ci_edges":[{"c":"5677331_c0","i":"022268_20180109","s":0.8966},{"c":"5677331_c0","i":"022268_20190806","s":0.9288},{"c":"5677331_c0","i":"022268_20120807","s":0.8406},{"c":"5677331_c0","i":"022268_20100223","s":0.8746},{"c":"5677331_c0","i":"022268_20090416","s":0.8366},{"c":"5677331_c0","i":"022268_20150320","s":0.847},{"c":"5677331_c0","i":"022268_20130501","s":0.847},{"c":"5677331_c1","i":"022268_20180109","s":0.8852},{"c":"5677331_c1","i":"022268_20190806","s":0.9419},{"c":"5677331_c1","i":"022268_20120807","s":0.852},{"c":"5677331_c1","i":"022268_20100223","s":0.8888},{"c":"5677331_c1","i":"022268_20090416","s":0.8453},{"c":"5677331_c1","i":"022268_20150320","s":0.8512},{"c":"5677331_c1","i":"022268_20130501","s":0.8512},{"c":"5677331_c2","i":"022268_20180109","s":0.8852},{"c":"5677331_c2","i":"022268_20190806","s":0.9419},{"c":"5677331_c2","i":"022268_20120807","s":0.852},{"c":"5677331_c2","i":"022268_20100223","s":0.8888},{"c":"5677331_c2","i":"022268_20090416","s":0.8453},{"c":"5677331_c2","i":"022268_20150320","s":0.8512},{"c":"5677331_c2","i":"022268_20130501","s":0.8512},{"c":"5677331_c3","i":"022268_20180109","s":0.8852},{"c":"5677331_c3","i":"022268_20190806","s":0.9419},{"c":"5677331_c3","i":"022268_20120807","s":0.852},{"c":"5677331_c3","i":"022268_20100223","s":0.8888},{"c":"5677331_c3","i":"022268_20090416","s":0.8453},{"c":"5677331_c3","i":"022268_20150320","s":0.8512},{"c":"5677331_c3","i":"022268_20130501","s":0.8512}]}