{"patents":[{"pat":"6696430","n_claims":4,"claims":[{"id":"6696430_c0","text":"What is claimed is: 1. A method of removing a retinal disorder membrane from an inner surface of a retina comprising the steps of: surgically opening an eye; applying a vital dye onto the retinal diso..."},{"id":"6696430_c1","text":"1. A method of removing a retinal disorder membrane from an inner surface of a retina comprising the steps of: surgically opening an eye; applying a vital dye onto the retinal disorder membrane locate..."},{"id":"6696430_c2","text":"1. A method of removing a retinal disorder membrane from an inner surface of a retina comprising the steps of: surgically opening an eye; applying a vital dye onto the retinal disorder membrane locate..."},{"id":"6696430_c3","text":"1. A method of removing a retinal disorder membrane from an inner surface of a retina comprising the steps of:"}]},{"pat":"6372449","n_claims":4,"claims":[{"id":"6372449_c0","text":"What is claimed is: 1. A method for the identification of intraocular membranes and structures within the eye, which comprises instilling into the eye a trypan blue solution which solution marks in a ..."},{"id":"6372449_c1","text":"1. A method for the identification of intraocular membranes and structures within the eye, which comprises instilling into the eye a trypan blue solution which solution marks in a visually identifiabl..."},{"id":"6372449_c2","text":"1. A method for the identification of intraocular membranes and structures within the eye, which comprises instilling into the eye a trypan blue solution which solution marks in a visually identifiabl..."},{"id":"6372449_c3","text":"1. A method for the identification of intraocular membranes and structures within the eye, which comprises instilling into the eye a trypan blue solution which solution marks in a visually identifiabl..."}]}],"use_codes":[{"code":"U-2377","desc":"USE OF VITAL DYE FOR FACILITATING SURGICAL PROCEDURES FOR VITREO-RETINAL SURGERY","iu":0.9235,"ug":-0.0094},{"code":"U-2379","desc":"USE IN IDENTIFICATION OF INTRAOCULAR MEMBRANES TO FACILITATE REMOVAL DURING OPHTHALMIC SURGERY","iu":0.9374,"ug":-0.002}],"edges":[{"c":"6696430_c0","u":"U-2377","s":0.9101,"g":-0.0134},{"c":"6696430_c1","u":"U-2377","s":0.9012,"g":-0.0223},{"c":"6696430_c2","u":"U-2377","s":0.9012,"g":-0.0223},{"c":"6696430_c3","u":"U-2377","s":0.8737,"g":-0.0498},{"c":"6372449_c0","u":"U-2377","s":0.9009,"g":-0.0226},{"c":"6372449_c1","u":"U-2377","s":0.9141,"g":-0.0094},{"c":"6372449_c2","u":"U-2377","s":0.9141,"g":-0.0094},{"c":"6372449_c3","u":"U-2377","s":0.9141,"g":-0.0094},{"c":"6696430_c0","u":"U-2379","s":0.9252,"g":-0.0122},{"c":"6696430_c1","u":"U-2379","s":0.9311,"g":-0.0063},{"c":"6696430_c2","u":"U-2379","s":0.9311,"g":-0.0063},{"c":"6696430_c3","u":"U-2379","s":0.925,"g":-0.0124},{"c":"6372449_c0","u":"U-2379","s":0.9344,"g":-0.003},{"c":"6372449_c1","u":"U-2379","s":0.9354,"g":-0.002},{"c":"6372449_c2","u":"U-2379","s":0.9354,"g":-0.002},{"c":"6372449_c3","u":"U-2379","s":0.9354,"g":-0.002}],"n_sparse":15,"sparse_threshold":0.88,"uc_years":{"U-2377":[2018,2019,2020,2021],"U-2379":[2018,2019,2020,2021]},"pat_ucs":{"6696430":["U-2377"],"6372449":["U-2379"]},"nda_gap":-0.0057,"ci_claims":[{"c":"6696430_c0","ci":0.9273},{"c":"6696430_c1","ci":0.9248},{"c":"6696430_c2","ci":0.9248},{"c":"6696430_c3","ci":0.9149},{"c":"6372449_c0","ci":0.9269},{"c":"6372449_c1","ci":0.9279},{"c":"6372449_c2","ci":0.9279},{"c":"6372449_c3","ci":0.9279}],"ci_mean":0.9253,"orphan_rate":0.0,"indications":[{"id":"022278_20251118","date":"20251118","text":"MembraneBlue\u2122 0.15% is indicated for use as an aid in ophthalmic surgery by staining the epiretinal\nmembranes during ophthalmic surgical vitrectomy procedures, facilitating removal of the tissue in adults\nand pediatric patients."},{"id":"022278_20140919","date":"20140919","text":"MembraneBlue\u2122 0.15% is indicated for use as an aid in ophthalmic surgery by staining the epiretinal membranes\nduring ophthalmic surgical vitrectomy procedures, facilitating removal of the tissue."}],"ci_edges":[{"c":"6696430_c0","i":"022278_20251118","s":0.9273},{"c":"6696430_c0","i":"022278_20140919","s":0.9268},{"c":"6696430_c1","i":"022278_20251118","s":0.9248},{"c":"6696430_c1","i":"022278_20140919","s":0.9248},{"c":"6696430_c2","i":"022278_20251118","s":0.9248},{"c":"6696430_c2","i":"022278_20140919","s":0.9248},{"c":"6696430_c3","i":"022278_20251118","s":0.9149},{"c":"6696430_c3","i":"022278_20140919","s":0.9146},{"c":"6372449_c0","i":"022278_20251118","s":0.9262},{"c":"6372449_c0","i":"022278_20140919","s":0.9269},{"c":"6372449_c1","i":"022278_20251118","s":0.9278},{"c":"6372449_c1","i":"022278_20140919","s":0.9279},{"c":"6372449_c2","i":"022278_20251118","s":0.9278},{"c":"6372449_c2","i":"022278_20140919","s":0.9279},{"c":"6372449_c3","i":"022278_20251118","s":0.9278},{"c":"6372449_c3","i":"022278_20140919","s":0.9279}],"ci_timeline":[{"y":2018,"ci":0.9252,"ci_max":0.9279,"n_claims":8,"n_weak":0},{"y":2019,"ci":0.9252,"ci_max":0.9279,"n_claims":8,"n_weak":0},{"y":2020,"ci":0.9252,"ci_max":0.9279,"n_claims":8,"n_weak":0},{"y":2021,"ci":0.9252,"ci_max":0.9279,"n_claims":8,"n_weak":0}]}