{"patents":[{"pat":"8178563","n_claims":13,"claims":[{"id":"8178563_ind_4","kind":"indep","text":"9. A method for inhibiting unwanted proliferation of a cell, comprising contacting the cell with a compound of claim 1 , wherein the cell is selected from pancreatic cancer, prostrate cancer, medullob..."},{"id":"8178563_ind_5","kind":"indep","text":"9. A method for inhibiting unwanted proliferation of a cell, comprising contacting the cell with a compound of claim 1 , wherein the cell is selected from pancreatic cancer, prostrate cancer, medullob..."},{"id":"8178563_ind_6","kind":"indep","text":"9. A method for inhibiting unwanted proliferation of a cell, comprising contacting the cell with a compound of claim 1 , wherein the cell is selected from pancreatic cancer, prostrate cancer, medullob..."},{"id":"8178563_dep_10","kind":"dep","text":"8. The method of claim 6 , wherein the compound is administered to an animal as part of a therapeutic application, wherein the therapeutic application is selected from pancreatic cancer, prostate canc..."},{"id":"8178563_dep_11","kind":"dep","text":"8. The method of claim 6 , wherein the compound is administered to an animal as part of a therapeutic application, wherein the therapeutic application is selected from pancreatic cancer, prostate canc..."},{"id":"8178563_dep_12","kind":"dep","text":"8. The method of claim 6 , wherein the compound is administered to an animal as part of a therapeutic application, wherein the therapeutic application is selected from pancreatic cancer, prostate canc..."}]}],"use_codes":[{"code":"U-1722","desc":"TREATMENT OF BASAL CELL CARCINOMA"}],"edges":[{"c":"8178563_ind_4","u":"U-1722","s":0.8965,"k":"indep"},{"c":"8178563_ind_5","u":"U-1722","s":0.8965,"k":"indep"},{"c":"8178563_ind_6","u":"U-1722","s":0.8965,"k":"indep"},{"c":"8178563_dep_10","u":"U-1722","s":0.9067,"k":"dep"},{"c":"8178563_dep_11","u":"U-1722","s":0.9067,"k":"dep"},{"c":"8178563_dep_12","u":"U-1722","s":0.9067,"k":"dep"}],"uc_years":{"U-1722":[2016,2017,2018,2019,2020,2021,2022,2023,2024]},"pat_ucs":{"8178563":["U-1722"]}}