{"patents":[{"pat":"11083698","n_claims":9,"claims":[{"id":"11083698_c0","text":"What is claimed is: 1. A method of administering epinephrine, comprising: providing a container comprising an antioxidant-free sterile epinephrine composition that is storage stable and contains epine..."},{"id":"11083698_c1","text":"1. A method of administering epinephrine, comprising: providing a container comprising an antioxidant-free sterile epinephrine composition that is storage stable and contains epinephrine in an aqueous..."},{"id":"11083698_c2","text":"1. A method of administering epinephrine, comprising: providing a container comprising an antioxidant-free sterile epinephrine composition that is storage stable and contains epinephrine in an aqueous..."},{"id":"11083698_c3","text":"1. A method of administering epinephrine, comprising: providing a container comprising an antioxidant-free sterile epinephrine composition that is storage stable and contains epinephrine in an aqueous..."},{"id":"11083698_c4","text":"administering the epinephrine composition via injection and without prior dilution from the container to a patient in need thereof."},{"id":"11083698_c5","text":"13. A method of increasing blood pressure in a patient, comprising: providing a container comprising an antioxidant-free sterile epinephrine composition that is storage stable and contains epinephrine..."},{"id":"11083698_c6","text":"13. A method of increasing blood pressure in a patient, comprising: providing a container comprising an antioxidant-free sterile epinephrine composition that is storage stable and contains epinephrine..."},{"id":"11083698_c7","text":"13. A method of increasing blood pressure in a patient, comprising: providing a container comprising an antioxidant-free sterile epinephrine composition that is storage stable and contains epinephrine..."},{"id":"11083698_c8","text":"administering the epinephrine composition via injection and without prior dilution from the container to the patient in need thereof."}]}],"use_codes":[{"code":"U-3567","desc":"TO INCREASE MEAN ARTERIAL BLOOD PRESSURE IN ADULT PATIENTS WITH HYPOTENSION ASSOCIATED WITH SEPTIC SHOCK","iu":0.9172,"ug":0.0054}],"edges":[{"c":"11083698_c0","u":"U-3567","s":0.8958,"g":-0.0214},{"c":"11083698_c1","u":"U-3567","s":0.8986,"g":-0.0186},{"c":"11083698_c2","u":"U-3567","s":0.8986,"g":-0.0186},{"c":"11083698_c3","u":"U-3567","s":0.8986,"g":-0.0186},{"c":"11083698_c4","u":"U-3567","s":0.8945,"g":-0.0227},{"c":"11083698_c5","u":"U-3567","s":0.9226,"g":0.0054},{"c":"11083698_c6","u":"U-3567","s":0.9226,"g":0.0054},{"c":"11083698_c7","u":"U-3567","s":0.9226,"g":0.0054},{"c":"11083698_c8","u":"U-3567","s":0.8934,"g":-0.0238}],"n_sparse":9,"sparse_threshold":0.88,"uc_years":{"U-3567":[2024]},"pat_ucs":{"11083698":["U-3567"]},"nda_gap":0.0054,"ci_claims":[{"c":"11083698_c0","ci":0.9318},{"c":"11083698_c1","ci":0.9386},{"c":"11083698_c2","ci":0.9386},{"c":"11083698_c3","ci":0.9386},{"c":"11083698_c4","ci":0.9206},{"c":"11083698_c5","ci":0.9452},{"c":"11083698_c6","ci":0.9452},{"c":"11083698_c7","ci":0.9452},{"c":"11083698_c8","ci":0.9197}],"ci_mean":0.9359,"orphan_rate":0.0,"indications":[{"id":"215875_20231024","date":"20231024","text":"Adrenalin\u00ae is a non-selective alpha and beta adrenergic agonist indicated to: Most common adverse reactions to systemically administered epinephrine are\nheadache; anxiety; apprehensiveness; restlessness; tremor; weakness;\n\uf0b7 Increase mean arterial blood pressure in adult patients with hypotension\ndiz..."},{"id":"215875_20230424","date":"20230424","text":"headache; anxiety; apprehensiveness; restlessness; tremor; weakness;\nEpinephrine in Sodium Chloride Injection is a non-selective alpha and beta\ndizziness; sweating; palpitations; pallor; peripheral coldness; nausea/vomiting;\nadrenergic agonist indicated to:\nand/or respiratory difficulties. Arrhythmi..."}],"ci_edges":[{"c":"11083698_c0","i":"215875_20231024","s":0.9318},{"c":"11083698_c0","i":"215875_20230424","s":0.929},{"c":"11083698_c1","i":"215875_20231024","s":0.9386},{"c":"11083698_c1","i":"215875_20230424","s":0.9373},{"c":"11083698_c2","i":"215875_20231024","s":0.9386},{"c":"11083698_c2","i":"215875_20230424","s":0.9373},{"c":"11083698_c3","i":"215875_20231024","s":0.9386},{"c":"11083698_c3","i":"215875_20230424","s":0.9373},{"c":"11083698_c4","i":"215875_20231024","s":0.9206},{"c":"11083698_c4","i":"215875_20230424","s":0.9153},{"c":"11083698_c5","i":"215875_20231024","s":0.9447},{"c":"11083698_c5","i":"215875_20230424","s":0.9452},{"c":"11083698_c6","i":"215875_20231024","s":0.9447},{"c":"11083698_c6","i":"215875_20230424","s":0.9452},{"c":"11083698_c7","i":"215875_20231024","s":0.9447},{"c":"11083698_c7","i":"215875_20230424","s":0.9452},{"c":"11083698_c8","i":"215875_20231024","s":0.9197},{"c":"11083698_c8","i":"215875_20230424","s":0.9147}],"ci_timeline":[{"y":2024,"ci":0.9358,"ci_max":0.9447,"n_claims":9,"n_weak":0}]}