{"008372":{"edges":21,"n_sparse":21,"size":3745},"008975":{"edges":184,"n_sparse":19,"size":15844},"012827":{"edges":4,"n_sparse":3,"size":1482},"013217":{"edges":174,"n_sparse":169,"size":21853},"013718":{"edges":41,"n_sparse":37,"size":11808},"016672":{"edges":54,"n_sparse":12,"size":6702},"016806":{"edges":54,"n_sparse":12,"size":6702},"017031":{"edges":54,"n_sparse":12,"size":7416},"017612":{"edges":54,"n_sparse":12,"size":7412},"017802":{"edges":54,"n_sparse":12,"size":7400},"017820":{"edges":8,"n_sparse":8,"size":1594},"017862":{"edges":8,"n_sparse":7,"size":1783},"018116":{"edges":14,"n_sparse":7,"size":2827},"018123":{"edges":24,"n_sparse":23,"size":3488},"018163":{"edges":14,"n_sparse":14,"size":4410},"018240":{"edges":12,"n_sparse":4,"size":1894},"018276":{"edges":4,"n_sparse":4,"size":1461},"018343":{"edges":13,"n_sparse":13,"size":4144},"018498":{"edges":14,"n_sparse":7,"size":2935},"018554":{"edges":54,"n_sparse":54,"size":7243},"018613":{"edges":8,"n_sparse":3,"size":2549},"018644":{"edges":4,"n_sparse":4,"size":1337},"018651":{"edges":4,"n_sparse":4,"size":1515},"018668":{"edges":54,"n_sparse":12,"size":7411},"018677":{"edges":48,"n_sparse":15,"size":5448},"018682":{"edges":4,"n_sparse":4,"size":1358},"018700":{"edges":8,"n_sparse":6,"size":1622},"018705":{"edges":2,"n_sparse":1,"size":724},"018708":{"edges":5,"n_sparse":5,"size":1813},"018731":{"edges":38,"n_sparse":23,"size":6405},"018770":{"edges":40,"n_sparse":12,"size":4590},"018782":{"edges":54,"n_sparse":12,"size":7426},"018859":{"edges":7,"n_sparse":7,"size":2404},"018869":{"edges":33,"n_sparse":11,"size":4728},"018917":{"edges":8,"n_sparse":8,"size":1722},"018922":{"edges":7,"n_sparse":7,"size":2256},"018936":{"edges":1520,"n_sparse":946,"size":85590},"018949":{"edges":4,"n_sparse":3,"size":1265},"019057":{"edges":57,"n_sparse":40,"size":7995},"019190":{"edges":66,"n_sparse":12,"size":8488},"019192":{"edges":66,"n_sparse":12,"size":8488},"019268":{"edges":4,"n_sparse":0,"size":1430},"019297":{"edges":28,"n_sparse":28,"size":5142},"019355":{"edges":4,"n_sparse":4,"size":1358},"019385":{"edges":21,"n_sparse":7,"size":3126},"019386":{"edges":8,"n_sparse":4,"size":1764},"019414":{"edges":1,"n_sparse":1,"size":616},"019415":{"edges":36,"n_sparse":36,"size":6321},"019439":{"edges":4,"n_sparse":4,"size":1419},"019507":{"edges":10,"n_sparse":3,"size":3248},"019508":{"edges":34,"n_sparse":28,"size":6007},"019530":{"edges":8,"n_sparse":4,"size":1823},"019537":{"edges":4,"n_sparse":3,"size":1491},"019546":{"edges":31,"n_sparse":18,"size":8783},"019548":{"edges":10,"n_sparse":3,"size":2992},"019568":{"edges":13,"n_sparse":3,"size":4176},"019583":{"edges":10,"n_sparse":9,"size":3128},"019593":{"edges":12,"n_sparse":10,"size":3894},"019614":{"edges":7,"n_sparse":6,"size":2335},"019616":{"edges":4,"n_sparse":4,"size":1367},"019627":{"edges":117,"n_sparse":117,"size":16238},"019645":{"edges":10,"n_sparse":6,"size":3140},"019651":{"edges":26,"n_sparse":25,"size":7762},"019658":{"edges":28,"n_sparse":25,"size":4585},"019661":{"edges":84,"n_sparse":84,"size":9206},"019664":{"edges":5,"n_sparse":3,"size":1605},"019670":{"edges":28,"n_sparse":25,"size":4575},"019677":{"edges":6,"n_sparse":6,"size":2081},"019678":{"edges":6,"n_sparse":6,"size":2081},"019693":{"edges":4,"n_sparse":4,"size":1368},"019697":{"edges":26,"n_sparse":10,"size":5030},"019698":{"edges":10,"n_sparse":6,"size":2977},"019700":{"edges":21,"n_sparse":11,"size":6516},"019710":{"edges":36,"n_sparse":20,"size":4477},"019715":{"edges":16,"n_sparse":16,"size":4925},"019722":{"edges":4,"n_sparse":4,"size":1400},"019729":{"edges":14,"n_sparse":7,"size":2822},"019734":{"edges":32,"n_sparse":30,"size":9522},"019757":{"edges":4,"n_sparse":4,"size":1380},"019763":{"edges":4,"n_sparse":4,"size":1492},"019766":{"edges":14,"n_sparse":13,"size":2850},"019778":{"edges":7,"n_sparse":6,"size":2295},"019779":{"edges":42,"n_sparse":28,"size":5881},"019785":{"edges":4,"n_sparse":0,"size":1402},"019787":{"edges":7,"n_sparse":6,"size":2078},"019798":{"edges":4,"n_sparse":4,"size":1429},"019806":{"edges":7,"n_sparse":7,"size":2338},"019807":{"edges":10,"n_sparse":3,"size":3232},"019810":{"edges":144,"n_sparse":128,"size":15913},"019813":{"edges":14,"n_sparse":4,"size":4378},"019834":{"edges":4,"n_sparse":3,"size":1420},"019835":{"edges":10,"n_sparse":9,"size":3197},"019839":{"edges":140,"n_sparse":132,"size":15262},"019863":{"edges":7,"n_sparse":7,"size":2002},"019880":{"edges":14,"n_sparse":14,"size":2720},"019881":{"edges":14,"n_sparse":14,"size":4455},"019884":{"edges":8,"n_sparse":4,"size":1810},"019885":{"edges":36,"n_sparse":33,"size":6479},"019888":{"edges":7,"n_sparse":6,"size":2294},"019890":{"edges":13,"n_sparse":13,"size":4039},"019898":{"edges":7,"n_sparse":7,"size":2475},"019901":{"edges":72,"n_sparse":62,"size":9366},"019908":{"edges":10,"n_sparse":10,"size":3193},"019921":{"edges":4,"n_sparse":4,"size":1477},"019937":{"edges":9,"n_sparse":9,"size":2801},"019940":{"edges":25,"n_sparse":9,"size":7183},"019960":{"edges":4,"n_sparse":4,"size":1367},"019961":{"edges":16,"n_sparse":12,"size":4457},"019962":{"edges":6,"n_sparse":3,"size":1938},"019963":{"edges":8,"n_sparse":7,"size":2537},"019976":{"edges":7,"n_sparse":6,"size":2054},"019981":{"edges":4,"n_sparse":1,"size":1501},"019982":{"edges":4,"n_sparse":4,"size":1475},"019983":{"edges":7,"n_sparse":6,"size":2217},"020007":{"edges":11,"n_sparse":11,"size":3532},"020013":{"edges":4,"n_sparse":3,"size":1485},"020031":{"edges":125,"n_sparse":96,"size":12662},"020035":{"edges":4,"n_sparse":3,"size":1482},"020036":{"edges":7,"n_sparse":0,"size":2291},"020043":{"edges":7,"n_sparse":6,"size":2036},"020049":{"edges":32,"n_sparse":25,"size":9513},"020059":{"edges":170,"n_sparse":132,"size":27268},"020062":{"edges":30,"n_sparse":20,"size":5403},"020068":{"edges":17,"n_sparse":17,"size":5215},"020070":{"edges":76,"n_sparse":40,"size":12113},"020076":{"edges":46,"n_sparse":45,"size":7866},"020080":{"edges":34,"n_sparse":30,"size":6094},"020101":{"edges":33,"n_sparse":33,"size":4684},"020103":{"edges":11,"n_sparse":11,"size":3524},"020114":{"edges":14,"n_sparse":14,"size":2902},"020118":{"edges":4,"n_sparse":4,"size":1505},"020123":{"edges":4,"n_sparse":4,"size":1507},"020125":{"edges":4,"n_sparse":3,"size":1410},"020126":{"edges":7,"n_sparse":7,"size":2378},"020130":{"edges":4,"n_sparse":3,"size":1462},"020131":{"edges":60,"n_sparse":44,"size":17613},"020132":{"edges":58,"n_sparse":50,"size":9851},"020134":{"edges":40,"n_sparse":40,"size":7068},"020144":{"edges":21,"n_sparse":10,"size":5914},"020148":{"edges":10,"n_sparse":4,"size":3246},"020152":{"edges":4,"n_sparse":4,"size":1355},"020154":{"edges":72,"n_sparse":71,"size":9697},"020155":{"edges":72,"n_sparse":71,"size":10033},"020156":{"edges":72,"n_sparse":71,"size":9697},"020164":{"edges":63,"n_sparse":61,"size":8689},"020165":{"edges":90,"n_sparse":82,"size":11455},"020180":{"edges":124,"n_sparse":94,"size":13936},"020182":{"edges":33,"n_sparse":33,"size":10089},"020184":{"edges":4,"n_sparse":4,"size":1569},"020186":{"edges":4,"n_sparse":4,"size":1471},"020189":{"edges":8,"n_sparse":8,"size":2673},"020191":{"edges":4,"n_sparse":4,"size":1438},"020192":{"edges":14,"n_sparse":12,"size":4213},"020193":{"edges":10,"n_sparse":10,"size":3148},"020195":{"edges":10,"n_sparse":9,"size":2991},"020199":{"edges":14,"n_sparse":14,"size":4421},"020208":{"edges":74,"n_sparse":74,"size":12334},"020210":{"edges":7,"n_sparse":6,"size":2252},"020212":{"edges":10,"n_sparse":9,"size":2763},"020213":{"edges":7,"n_sparse":4,"size":2313},"020220":{"edges":4,"n_sparse":4,"size":1416},"020221":{"edges":25,"n_sparse":25,"size":7540},"020235":{"edges":16,"n_sparse":11,"size":3101},"020236":{"edges":7,"n_sparse":7,"size":2368},"020239":{"edges":40,"n_sparse":26,"size":6987},"020240":{"edges":7,"n_sparse":6,"size":1969},"020241":{"edges":7,"n_sparse":6,"size":2330},"020256":{"edges":118,"n_sparse":103,"size":19407},"020258":{"edges":4,"n_sparse":4,"size":1466},"020259":{"edges":22,"n_sparse":13,"size":5291},"020261":{"edges":14,"n_sparse":10,"size":3148},"020262":{"edges":201,"n_sparse":201,"size":26951},"020263":{"edges":7,"n_sparse":3,"size":2328},"020272":{"edges":11,"n_sparse":10,"size":3553},"020273":{"edges":4,"n_sparse":3,"size":1437},"020279":{"edges":13,"n_sparse":3,"size":4166},"020281":{"edges":4,"n_sparse":4,"size":1571},"020297":{"edges":87,"n_sparse":59,"size":11200},"020303":{"edges":28,"n_sparse":26,"size":4813},"020305":{"edges":16,"n_sparse":3,"size":4909},"020310":{"edges":4,"n_sparse":4,"size":1219},"020313":{"edges":4,"n_sparse":0,"size":1488},"020314":{"edges":14,"n_sparse":14,"size":4409},"020325":{"edges":16,"n_sparse":16,"size":3188},"020326":{"edges":7,"n_sparse":7,"size":2458},"020329":{"edges":168,"n_sparse":141,"size":21117},"020336":{"edges":130,"n_sparse":33,"size":35001},"020338":{"edges":2,"n_sparse":0,"size":708},"020344":{"edges":4,"n_sparse":4,"size":1414},"020347":{"edges":22,"n_sparse":15,"size":4287},"020356":{"edges":13,"n_sparse":12,"size":3340},"020363":{"edges":44,"n_sparse":43,"size":13132},"020364":{"edges":8,"n_sparse":8,"size":1878},"020367":{"edges":13,"n_sparse":12,"size":3982},"020369":{"edges":4,"n_sparse":3,"size":1413},"020378":{"edges":4,"n_sparse":4,"size":1388},"020379":{"edges":4,"n_sparse":4,"size":1339},"020380":{"edges":2,"n_sparse":0,"size":708},"020381":{"edges":1674,"n_sparse":1669,"size":103641},"020386":{"edges":34,"n_sparse":21,"size":6069},"020387":{"edges":8,"n_sparse":8,"size":2011},"020393":{"edges":4,"n_sparse":4,"size":1441},"020394":{"edges":4,"n_sparse":4,"size":1356},"020398":{"edges":7,"n_sparse":6,"size":2237},"020403":{"edges":11,"n_sparse":11,"size":3514},"020404":{"edges":16,"n_sparse":15,"size":3071},"020406":{"edges":22,"n_sparse":18,"size":4157},"020408":{"edges":28,"n_sparse":25,"size":5087},"020410":{"edges":132,"n_sparse":132,"size":16639},"020411":{"edges":1,"n_sparse":1,"size":643},"020412":{"edges":7,"n_sparse":7,"size":2527},"020416":{"edges":111,"n_sparse":109,"size":14048},"020420":{"edges":48,"n_sparse":0,"size":13240},"020428":{"edges":4,"n_sparse":3,"size":1426},"020444":{"edges":7,"n_sparse":7,"size":2115},"020451":{"edges":12,"n_sparse":11,"size":2461},"020452":{"edges":7,"n_sparse":7,"size":2287},"020457":{"edges":4,"n_sparse":3,"size":1463},"020460":{"edges":21,"n_sparse":21,"size":5928},"020468":{"edges":70,"n_sparse":45,"size":12675},"020470":{"edges":28,"n_sparse":25,"size":4570},"020471":{"edges":7,"n_sparse":6,"size":2334},"020472":{"edges":8,"n_sparse":8,"size":2719},"020474":{"edges":4,"n_sparse":4,"size":1497},"020475":{"edges":32,"n_sparse":0,"size":9643},"020479":{"edges":8,"n_sparse":4,"size":2530},"020487":{"edges":62,"n_sparse":61,"size":11426},"020489":{"edges":10,"n_sparse":10,"size":2980},"020496":{"edges":4,"n_sparse":3,"size":1465},"020497":{"edges":7,"n_sparse":6,"size":2405},"020498":{"edges":30,"n_sparse":21,"size":5471},"020500":{"edges":26,"n_sparse":16,"size":6818},"020503":{"edges":7,"n_sparse":7,"size":2172},"020505":{"edges":212,"n_sparse":148,"size":23674},"020507":{"edges":7,"n_sparse":6,"size":2148},"020509":{"edges":4,"n_sparse":4,"size":1519},"020511":{"edges":4,"n_sparse":3,"size":1390},"020517":{"edges":16,"n_sparse":6,"size":3238},"020519":{"edges":10,"n_sparse":10,"size":3313},"020520":{"edges":11,"n_sparse":9,"size":3363},"020524":{"edges":4,"n_sparse":3,"size":1463},"020527":{"edges":28,"n_sparse":26,"size":5013},"020528":{"edges":4,"n_sparse":4,"size":1515},"020533":{"edges":46,"n_sparse":46,"size":7156},"020539":{"edges":16,"n_sparse":12,"size":3050},"020547":{"edges":7,"n_sparse":7,"size":2386},"020549":{"edges":10,"n_sparse":10,"size":2853},"020551":{"edges":4,"n_sparse":3,"size":1511},"020552":{"edges":225,"n_sparse":216,"size":27906},"020553":{"edges":17,"n_sparse":17,"size":5115},"020559":{"edges":1480,"n_sparse":1479,"size":133992},"020560":{"edges":90,"n_sparse":90,"size":12333},"020563":{"edges":344,"n_sparse":338,"size":32307},"020564":{"edges":66,"n_sparse":62,"size":11459},"020570":{"edges":13,"n_sparse":12,"size":4059},"020571":{"edges":20,"n_sparse":20,"size":4237},"020572":{"edges":4,"n_sparse":4,"size":1461},"020573":{"edges":4,"n_sparse":4,"size":1461},"020579":{"edges":4,"n_sparse":4,"size":1489},"020582":{"edges":4,"n_sparse":4,"size":1429},"020583":{"edges":4,"n_sparse":4,"size":1525},"020586":{"edges":46,"n_sparse":26,"size":7899},"020588":{"edges":7,"n_sparse":6,"size":2332},"020592":{"edges":621,"n_sparse":587,"size":45796},"020596":{"edges":11,"n_sparse":10,"size":3492},"020597":{"edges":92,"n_sparse":92,"size":13267},"020600":{"edges":27,"n_sparse":22,"size":4119},"020605":{"edges":38,"n_sparse":35,"size":6916},"020606":{"edges":7,"n_sparse":7,"size":2327},"020607":{"edges":4,"n_sparse":4,"size":1466},"020610":{"edges":14,"n_sparse":3,"size":4417},"020612":{"edges":104,"n_sparse":100,"size":11978},"020613":{"edges":12,"n_sparse":0,"size":3847},"020617":{"edges":22,"n_sparse":22,"size":6407},"020619":{"edges":7,"n_sparse":7,"size":2290},"020622":{"edges":62,"n_sparse":57,"size":18359},"020625":{"edges":188,"n_sparse":165,"size":20389},"020626":{"edges":48,"n_sparse":45,"size":7743},"020629":{"edges":72,"n_sparse":72,"size":21405},"020630":{"edges":22,"n_sparse":20,"size":4083},"020632":{"edges":4,"n_sparse":4,"size":1459},"020636":{"edges":7,"n_sparse":7,"size":2351},"020639":{"edges":7,"n_sparse":3,"size":1971},"020641":{"edges":28,"n_sparse":25,"size":4565},"020652":{"edges":34,"n_sparse":34,"size":6168},"020658":{"edges":10,"n_sparse":10,"size":3195},"020659":{"edges":320,"n_sparse":316,"size":33508},"020665":{"edges":4,"n_sparse":3,"size":1475},"020667":{"edges":144,"n_sparse":100,"size":24410},"020668":{"edges":24,"n_sparse":21,"size":6619},"020671":{"edges":26,"n_sparse":20,"size":4848},"020675":{"edges":4,"n_sparse":4,"size":1377},"020677":{"edges":7,"n_sparse":6,"size":2231},"020680":{"edges":96,"n_sparse":94,"size":15207},"020682":{"edges":7,"n_sparse":6,"size":2323},"020685":{"edges":58,"n_sparse":47,"size":9377},"020688":{"edges":28,"n_sparse":27,"size":5145},"020689":{"edges":4,"n_sparse":3,"size":1361},"020692":{"edges":34,"n_sparse":30,"size":6232},"020697":{"edges":7,"n_sparse":7,"size":2348},"020698":{"edges":22,"n_sparse":18,"size":3912},"020699":{"edges":310,"n_sparse":218,"size":30792},"020700":{"edges":29,"n_sparse":25,"size":8879},"020701":{"edges":54,"n_sparse":44,"size":9329},"020702":{"edges":124,"n_sparse":116,"size":13162},"020704":{"edges":28,"n_sparse":25,"size":4565},"020706":{"edges":10,"n_sparse":8,"size":2153},"020710":{"edges":88,"n_sparse":65,"size":10361},"020712":{"edges":16,"n_sparse":15,"size":3130},"020716":{"edges":10,"n_sparse":10,"size":3152},"020717":{"edges":11,"n_sparse":3,"size":3521},"020718":{"edges":40,"n_sparse":40,"size":7131},"020719":{"edges":1152,"n_sparse":1144,"size":95600},"020720":{"edges":1152,"n_sparse":1144,"size":100060},"020723":{"edges":69,"n_sparse":43,"size":9269},"020725":{"edges":5,"n_sparse":4,"size":1656},"020726":{"edges":28,"n_sparse":27,"size":8321},"020727":{"edges":63,"n_sparse":63,"size":18343},"020738":{"edges":32,"n_sparse":27,"size":8725},"020741":{"edges":32,"n_sparse":32,"size":4091},"020746":{"edges":64,"n_sparse":60,"size":11593},"020747":{"edges":10,"n_sparse":3,"size":3079},"020749":{"edges":4,"n_sparse":0,"size":1405},"020752":{"edges":4,"n_sparse":4,"size":1639},"020753":{"edges":7,"n_sparse":4,"size":2298},"020759":{"edges":8,"n_sparse":6,"size":2689},"020760":{"edges":8,"n_sparse":6,"size":2689},"020762":{"edges":52,"n_sparse":49,"size":8924},"020763":{"edges":10,"n_sparse":9,"size":3189},"020764":{"edges":7,"n_sparse":6,"size":2315},"020767":{"edges":7,"n_sparse":6,"size":2232},"020771":{"edges":7,"n_sparse":3,"size":2300},"020776":{"edges":7,"n_sparse":6,"size":2356},"020778":{"edges":22,"n_sparse":18,"size":4020},"020779":{"edges":22,"n_sparse":18,"size":4020},"020780":{"edges":4,"n_sparse":3,"size":1298},"020781":{"edges":30,"n_sparse":28,"size":5582},"020785":{"edges":1368,"n_sparse":1109,"size":97998},"020786":{"edges":160,"n_sparse":147,"size":17616},"020788":{"edges":22,"n_sparse":22,"size":4591},"020789":{"edges":10,"n_sparse":10,"size":3040},"020791":{"edges":4,"n_sparse":4,"size":1486},"020796":{"edges":46,"n_sparse":16,"size":13624},"020799":{"edges":4,"n_sparse":4,"size":1380},"020801":{"edges":4,"n_sparse":4,"size":1591},"020802":{"edges":19,"n_sparse":19,"size":5713},"020803":{"edges":4,"n_sparse":4,"size":1481},"020805":{"edges":4,"n_sparse":4,"size":1457},"020809":{"edges":5,"n_sparse":5,"size":1909},"020815":{"edges":365,"n_sparse":332,"size":35075},"020816":{"edges":62,"n_sparse":27,"size":9976},"020818":{"edges":11,"n_sparse":9,"size":3549},"020819":{"edges":16,"n_sparse":16,"size":3340},"020823":{"edges":14,"n_sparse":13,"size":4414},"020825":{"edges":16,"n_sparse":14,"size":3020},"020829":{"edges":57,"n_sparse":33,"size":7268},"020830":{"edges":57,"n_sparse":33,"size":7268},"020831":{"edges":7,"n_sparse":7,"size":2367},"020832":{"edges":4,"n_sparse":4,"size":1437},"020833":{"edges":10,"n_sparse":10,"size":2850},"020835":{"edges":370,"n_sparse":348,"size":36202},"020837":{"edges":64,"n_sparse":64,"size":11155},"020838":{"edges":28,"n_sparse":25,"size":5099},"020839":{"edges":7,"n_sparse":7,"size":2522},"020844":{"edges":285,"n_sparse":179,"size":26679},"020845":{"edges":3280,"n_sparse":3247,"size":244040},"020846":{"edges":80,"n_sparse":34,"size":9410},"020850":{"edges":36,"n_sparse":27,"size":5148},"020857":{"edges":88,"n_sparse":82,"size":15002},"020862":{"edges":86,"n_sparse":46,"size":15373},"020864":{"edges":8,"n_sparse":6,"size":2698},"020865":{"edges":8,"n_sparse":6,"size":2698},"020866":{"edges":42592,"n_sparse":42396,"size":2460875},"020868":{"edges":4,"n_sparse":3,"size":1446},"020869":{"edges":54,"n_sparse":51,"size":7664},"020872":{"edges":220,"n_sparse":203,"size":21338},"020873":{"edges":32,"n_sparse":32,"size":6123},"020882":{"edges":16,"n_sparse":10,"size":3036},"020884":{"edges":13,"n_sparse":12,"size":3546},"020885":{"edges":130,"n_sparse":96,"size":12506},"020886":{"edges":8,"n_sparse":7,"size":2636},"020895":{"edges":10,"n_sparse":10,"size":3193},"020896":{"edges":22,"n_sparse":12,"size":4133},"020897":{"edges":297,"n_sparse":293,"size":37489},"020898":{"edges":4,"n_sparse":4,"size":1405},"020899":{"edges":23,"n_sparse":22,"size":6860},"020902":{"edges":8,"n_sparse":8,"size":2549},"020903":{"edges":960,"n_sparse":960,"size":73180},"020905":{"edges":15,"n_sparse":13,"size":4600},"020906":{"edges":4,"n_sparse":3,"size":1353},"020908":{"edges":7,"n_sparse":7,"size":2445},"020911":{"edges":16,"n_sparse":9,"size":3072},"020912":{"edges":155,"n_sparse":136,"size":15534},"020913":{"edges":45,"n_sparse":37,"size":6534},"020919":{"edges":4,"n_sparse":4,"size":1332},"020920":{"edges":22,"n_sparse":21,"size":4083},"020922":{"edges":5,"n_sparse":3,"size":1849},"020926":{"edges":23,"n_sparse":21,"size":6996},"020929":{"edges":300,"n_sparse":274,"size":32121},"020931":{"edges":4,"n_sparse":3,"size":1454},"020934":{"edges":7,"n_sparse":7,"size":2404},"020936":{"edges":75,"n_sparse":73,"size":10411},"020941":{"edges":14,"n_sparse":14,"size":4291},"020945":{"edges":372,"n_sparse":368,"size":40074},"020946":{"edges":1,"n_sparse":1,"size":808},"020947":{"edges":156,"n_sparse":152,"size":18508},"020949":{"edges":22,"n_sparse":22,"size":5419},"020950":{"edges":9,"n_sparse":9,"size":2968},"020954":{"edges":52,"n_sparse":52,"size":9621},"020958":{"edges":21,"n_sparse":0,"size":6062},"020961":{"edges":52,"n_sparse":52,"size":14857},"020965":{"edges":280,"n_sparse":243,"size":46282},"020969":{"edges":4,"n_sparse":0,"size":1464},"020972":{"edges":108,"n_sparse":108,"size":14123},"020973":{"edges":8,"n_sparse":7,"size":2518},"020974":{"edges":14,"n_sparse":14,"size":2735},"020977":{"edges":40,"n_sparse":40,"size":7015},"020978":{"edges":42,"n_sparse":40,"size":7404},"020980":{"edges":8,"n_sparse":6,"size":2442},"020981":{"edges":9,"n_sparse":0,"size":2870},"020983":{"edges":99,"n_sparse":95,"size":12478},"020985":{"edges":28,"n_sparse":6,"size":6952},"020989":{"edges":16,"n_sparse":15,"size":3116},"020990":{"edges":170,"n_sparse":130,"size":16064},"020997":{"edges":4,"n_sparse":4,"size":1409},"020998":{"edges":207,"n_sparse":70,"size":17394},"021001":{"edges":4,"n_sparse":3,"size":1435},"021003":{"edges":4,"n_sparse":4,"size":1523},"021004":{"edges":4,"n_sparse":4,"size":1523},"021005":{"edges":42,"n_sparse":28,"size":12529},"021006":{"edges":52,"n_sparse":47,"size":9378},"021007":{"edges":16,"n_sparse":13,"size":4901},"021008":{"edges":28,"n_sparse":14,"size":5085},"021009":{"edges":4,"n_sparse":4,"size":1562},"021014":{"edges":7,"n_sparse":7,"size":2333},"021015":{"edges":16,"n_sparse":16,"size":4978},"021016":{"edges":37,"n_sparse":33,"size":10997},"021017":{"edges":180,"n_sparse":174,"size":25806},"021018":{"edges":180,"n_sparse":174,"size":25806},"021022":{"edges":4,"n_sparse":4,"size":1400},"021025":{"edges":14,"n_sparse":13,"size":4414},"021026":{"edges":28,"n_sparse":28,"size":5112},"021027":{"edges":17,"n_sparse":17,"size":5358},"021029":{"edges":18,"n_sparse":15,"size":5492},"021036":{"edges":30,"n_sparse":0,"size":4571},"021038":{"edges":100,"n_sparse":84,"size":11129},"021039":{"edges":16,"n_sparse":13,"size":4887},"021040":{"edges":24,"n_sparse":19,"size":4893},"021041":{"edges":15,"n_sparse":7,"size":4758},"021042":{"edges":72,"n_sparse":72,"size":12860},"021044":{"edges":42,"n_sparse":41,"size":11062},"021052":{"edges":29,"n_sparse":29,"size":8972},"021055":{"edges":268,"n_sparse":212,"size":45247},"021056":{"edges":112,"n_sparse":98,"size":32954},"021057":{"edges":4,"n_sparse":4,"size":1523},"021060":{"edges":159,"n_sparse":131,"size":21426},"021064":{"edges":182,"n_sparse":159,"size":50882},"021065":{"edges":4,"n_sparse":4,"size":1505},"021066":{"edges":4,"n_sparse":4,"size":1434},"021067":{"edges":64,"n_sparse":62,"size":18961},"021071":{"edges":84,"n_sparse":81,"size":9277},"021073":{"edges":473,"n_sparse":466,"size":34186},"021074":{"edges":65,"n_sparse":64,"size":16449},"021075":{"edges":4,"n_sparse":4,"size":1476},"021077":{"edges":124,"n_sparse":115,"size":14320},"021078":{"edges":30,"n_sparse":29,"size":5704},"021079":{"edges":19,"n_sparse":19,"size":5548},"021081":{"edges":76,"n_sparse":60,"size":8418},"021083":{"edges":64,"n_sparse":64,"size":7665},"021085":{"edges":31,"n_sparse":25,"size":9111},"021086":{"edges":366,"n_sparse":366,"size":31947},"021087":{"edges":7,"n_sparse":7,"size":2158},"021088":{"edges":4,"n_sparse":3,"size":1288},"021093":{"edges":38,"n_sparse":34,"size":11280},"021097":{"edges":9,"n_sparse":0,"size":2820},"021098":{"edges":7,"n_sparse":3,"size":2318},"021106":{"edges":23,"n_sparse":20,"size":6972},"021107":{"edges":23,"n_sparse":22,"size":6781},"021108":{"edges":4,"n_sparse":4,"size":1432},"021110":{"edges":100,"n_sparse":80,"size":10080},"021114":{"edges":14,"n_sparse":12,"size":2635},"021119":{"edges":33,"n_sparse":26,"size":9561},"021121":{"edges":680,"n_sparse":405,"size":67826},"021124":{"edges":24,"n_sparse":10,"size":4168},"021129":{"edges":4,"n_sparse":4,"size":1424},"021130":{"edges":4,"n_sparse":3,"size":1441},"021131":{"edges":4,"n_sparse":3,"size":1441},"021132":{"edges":4,"n_sparse":3,"size":1441},"021140":{"edges":7,"n_sparse":7,"size":2253},"021141":{"edges":59,"n_sparse":49,"size":17495},"021142":{"edges":7,"n_sparse":7,"size":2403},"021144":{"edges":4,"n_sparse":4,"size":1663},"021145":{"edges":17,"n_sparse":10,"size":5190},"021148":{"edges":34,"n_sparse":34,"size":5852},"021150":{"edges":21,"n_sparse":19,"size":6541},"021152":{"edges":4,"n_sparse":4,"size":1454},"021153":{"edges":876,"n_sparse":790,"size":78072},"021158":{"edges":252,"n_sparse":252,"size":24479},"021159":{"edges":22,"n_sparse":22,"size":4256},"021160":{"edges":7,"n_sparse":6,"size":2181},"021162":{"edges":4,"n_sparse":3,"size":1407},"021164":{"edges":4,"n_sparse":4,"size":1615},"021165":{"edges":441,"n_sparse":344,"size":34282},"021168":{"edges":28,"n_sparse":23,"size":4816},"021169":{"edges":8,"n_sparse":8,"size":2692},"021172":{"edges":35,"n_sparse":35,"size":9074},"021174":{"edges":25,"n_sparse":12,"size":6691},"021176":{"edges":210,"n_sparse":131,"size":27005},"021178":{"edges":7,"n_sparse":6,"size":2108},"021179":{"edges":34,"n_sparse":30,"size":10242},"021180":{"edges":42,"n_sparse":29,"size":11062},"021183":{"edges":14,"n_sparse":13,"size":4162},"021184":{"edges":4,"n_sparse":4,"size":1531},"021191":{"edges":51,"n_sparse":36,"size":15098},"021192":{"edges":14,"n_sparse":10,"size":3118},"021196":{"edges":2596,"n_sparse":2158,"size":179703},"021197":{"edges":23,"n_sparse":22,"size":6601},"021200":{"edges":7,"n_sparse":6,"size":2337},"021202":{"edges":13,"n_sparse":13,"size":4127},"021204":{"edges":6,"n_sparse":3,"size":1615},"021205":{"edges":204,"n_sparse":200,"size":34311},"021211":{"edges":216,"n_sparse":185,"size":16789},"021214":{"edges":135,"n_sparse":121,"size":17094},"021217":{"edges":35,"n_sparse":10,"size":10463},"021223":{"edges":69,"n_sparse":28,"size":9861},"021224":{"edges":4,"n_sparse":4,"size":1441},"021225":{"edges":45,"n_sparse":45,"size":7015},"021226":{"edges":1630,"n_sparse":1603,"size":117384},"021227":{"edges":33,"n_sparse":32,"size":9798},"021228":{"edges":80,"n_sparse":70,"size":12813},"021235":{"edges":28,"n_sparse":20,"size":5403},"021238":{"edges":16,"n_sparse":3,"size":4879},"021241":{"edges":20,"n_sparse":15,"size":6372},"021246":{"edges":14,"n_sparse":11,"size":2705},"021248":{"edges":258,"n_sparse":258,"size":25389},"021249":{"edges":1488,"n_sparse":1481,"size":89675},"021251":{"edges":1640,"n_sparse":1611,"size":110547},"021253":{"edges":4,"n_sparse":3,"size":1495},"021254":{"edges":201,"n_sparse":200,"size":25515},"021257":{"edges":54,"n_sparse":40,"size":9986},"021262":{"edges":81,"n_sparse":37,"size":10842},"021266":{"edges":39,"n_sparse":39,"size":10463},"021267":{"edges":39,"n_sparse":39,"size":10463},"021268":{"edges":32,"n_sparse":27,"size":8704},"021272":{"edges":228,"n_sparse":219,"size":22328},"021273":{"edges":11,"n_sparse":10,"size":3163},"021275":{"edges":17,"n_sparse":14,"size":4999},"021277":{"edges":34,"n_sparse":28,"size":9948},"021278":{"edges":36,"n_sparse":36,"size":5335},"021281":{"edges":22,"n_sparse":18,"size":4117},"021282":{"edges":8,"n_sparse":0,"size":2563},"021283":{"edges":24,"n_sparse":23,"size":4748},"021284":{"edges":46,"n_sparse":45,"size":8241},"021285":{"edges":17,"n_sparse":16,"size":5268},"021286":{"edges":16,"n_sparse":14,"size":3240},"021287":{"edges":4,"n_sparse":0,"size":1452},"021299":{"edges":21,"n_sparse":18,"size":3377},"021300":{"edges":72,"n_sparse":69,"size":8212},"021301":{"edges":4,"n_sparse":4,"size":1512},"021304":{"edges":8,"n_sparse":8,"size":1947},"021306":{"edges":34,"n_sparse":34,"size":6660},"021312":{"edges":336,"n_sparse":321,"size":26665},"021313":{"edges":321,"n_sparse":280,"size":41409},"021316":{"edges":4,"n_sparse":4,"size":1676},"021318":{"edges":161,"n_sparse":151,"size":16269},"021319":{"edges":28,"n_sparse":26,"size":5676},"021320":{"edges":35,"n_sparse":24,"size":10249},"021321":{"edges":14,"n_sparse":13,"size":4537},"021324":{"edges":11,"n_sparse":11,"size":3688},"021332":{"edges":520,"n_sparse":514,"size":47294},"021335":{"edges":32,"n_sparse":27,"size":6220},"021337":{"edges":20,"n_sparse":19,"size":5116},"021338":{"edges":95,"n_sparse":64,"size":27925},"021341":{"edges":7,"n_sparse":6,"size":2420},"021343":{"edges":27,"n_sparse":10,"size":7549},"021344":{"edges":160,"n_sparse":155,"size":18190},"021346":{"edges":44,"n_sparse":24,"size":8222},"021350":{"edges":4,"n_sparse":4,"size":1687},"021351":{"edges":50,"n_sparse":41,"size":14378},"021356":{"edges":90,"n_sparse":71,"size":10122},"021359":{"edges":7,"n_sparse":7,"size":2403},"021360":{"edges":58,"n_sparse":58,"size":10117},"021361":{"edges":1920,"n_sparse":1438,"size":138542},"021366":{"edges":45,"n_sparse":45,"size":7112},"021367":{"edges":7,"n_sparse":7,"size":2517},"021368":{"edges":172,"n_sparse":151,"size":20338},"021372":{"edges":48,"n_sparse":46,"size":8529},"021378":{"edges":10,"n_sparse":10,"size":2795},"021379":{"edges":68,"n_sparse":32,"size":11030},"021385":{"edges":13,"n_sparse":9,"size":3979},"021387":{"edges":7,"n_sparse":7,"size":2465},"021392":{"edges":114,"n_sparse":105,"size":33242},"021393":{"edges":7,"n_sparse":7,"size":2370},"021395":{"edges":168,"n_sparse":162,"size":22165},"021398":{"edges":368,"n_sparse":366,"size":33245},"021399":{"edges":4,"n_sparse":3,"size":1472},"021400":{"edges":58,"n_sparse":40,"size":9343},"021406":{"edges":29,"n_sparse":12,"size":8714},"021409":{"edges":38,"n_sparse":27,"size":6602},"021410":{"edges":116,"n_sparse":107,"size":12616},"021411":{"edges":4,"n_sparse":4,"size":1386},"021415":{"edges":8,"n_sparse":0,"size":2633},"021425":{"edges":8,"n_sparse":4,"size":1715},"021427":{"edges":261,"n_sparse":124,"size":18804},"021428":{"edges":22,"n_sparse":18,"size":4127},"021433":{"edges":176,"n_sparse":176,"size":18999},"021436":{"edges":2205,"n_sparse":1815,"size":176849},"021437":{"edges":285,"n_sparse":261,"size":30362},"021443":{"edges":56,"n_sparse":41,"size":6986},"021444":{"edges":16,"n_sparse":6,"size":3193},"021445":{"edges":145,"n_sparse":143,"size":14990},"021446":{"edges":75,"n_sparse":52,"size":8236},"021449":{"edges":23,"n_sparse":7,"size":6238},"021450":{"edges":7,"n_sparse":7,"size":2023},"021451":{"edges":4,"n_sparse":4,"size":1627},"021453":{"edges":22,"n_sparse":20,"size":4109},"021454":{"edges":147,"n_sparse":133,"size":19932},"021455":{"edges":210,"n_sparse":183,"size":21331},"021457":{"edges":36,"n_sparse":33,"size":5115},"021462":{"edges":51,"n_sparse":51,"size":7136},"021463":{"edges":16,"n_sparse":13,"size":4942},"021468":{"edges":28,"n_sparse":20,"size":4800},"021470":{"edges":16,"n_sparse":16,"size":5063},"021476":{"edges":24,"n_sparse":16,"size":4554},"021481":{"edges":7,"n_sparse":7,"size":2323},"021483":{"edges":57,"n_sparse":49,"size":7328},"021485":{"edges":55,"n_sparse":18,"size":16132},"021487":{"edges":14,"n_sparse":7,"size":3600},"021488":{"edges":68,"n_sparse":32,"size":11030},"021489":{"edges":60,"n_sparse":47,"size":17654},"021490":{"edges":7,"n_sparse":0,"size":2334},"021497":{"edges":40,"n_sparse":31,"size":7045},"021498":{"edges":72,"n_sparse":54,"size":9649},"021500":{"edges":114,"n_sparse":114,"size":20692},"021502":{"edges":2,"n_sparse":0,"size":894},"021503":{"edges":22,"n_sparse":18,"size":3995},"021506":{"edges":38,"n_sparse":26,"size":6724},"021513":{"edges":16,"n_sparse":12,"size":3295},"021514":{"edges":48,"n_sparse":42,"size":8519},"021520":{"edges":10,"n_sparse":10,"size":3241},"021526":{"edges":163,"n_sparse":163,"size":47533},"021527":{"edges":11,"n_sparse":11,"size":3577},"021528":{"edges":322,"n_sparse":322,"size":29760},"021529":{"edges":26,"n_sparse":6,"size":4600},"021532":{"edges":16,"n_sparse":14,"size":3223},"021536":{"edges":27,"n_sparse":27,"size":7950},"021537":{"edges":32,"n_sparse":31,"size":5912},"021539":{"edges":80,"n_sparse":76,"size":13545},"021540":{"edges":205,"n_sparse":178,"size":19237},"021543":{"edges":10,"n_sparse":10,"size":3274},"021544":{"edges":8,"n_sparse":7,"size":1910},"021545":{"edges":14,"n_sparse":13,"size":4435},"021546":{"edges":234,"n_sparse":234,"size":31579},"021548":{"edges":16,"n_sparse":9,"size":4557},"021549":{"edges":704,"n_sparse":535,"size":53652},"021551":{"edges":7,"n_sparse":5,"size":2232},"021560":{"edges":88,"n_sparse":68,"size":15140},"021565":{"edges":8,"n_sparse":8,"size":2474},"021566":{"edges":13,"n_sparse":13,"size":4207},"021567":{"edges":4,"n_sparse":3,"size":1473},"021571":{"edges":4,"n_sparse":4,"size":1515},"021572":{"edges":108,"n_sparse":99,"size":13266},"021574":{"edges":11,"n_sparse":11,"size":3595},"021585":{"edges":7,"n_sparse":3,"size":2237},"021588":{"edges":36,"n_sparse":31,"size":5589},"021597":{"edges":25,"n_sparse":13,"size":5532},"021598":{"edges":24,"n_sparse":20,"size":7279},"021602":{"edges":204,"n_sparse":76,"size":25362},"021605":{"edges":132,"n_sparse":125,"size":14137},"021606":{"edges":16,"n_sparse":16,"size":3345},"021610":{"edges":32,"n_sparse":24,"size":5484},"021612":{"edges":10,"n_sparse":10,"size":3202},"021615":{"edges":4,"n_sparse":4,"size":1432},"021620":{"edges":7,"n_sparse":6,"size":2236},"021621":{"edges":36,"n_sparse":23,"size":6225},"021627":{"edges":4,"n_sparse":4,"size":1493},"021629":{"edges":78,"n_sparse":65,"size":9948},"021630":{"edges":39,"n_sparse":39,"size":10458},"021632":{"edges":46,"n_sparse":43,"size":12075},"021633":{"edges":4,"n_sparse":4,"size":1575},"021636":{"edges":135,"n_sparse":72,"size":17724},"021641":{"edges":21,"n_sparse":11,"size":6387},"021642":{"edges":114,"n_sparse":114,"size":15378},"021644":{"edges":34,"n_sparse":25,"size":8420},"021652":{"edges":44,"n_sparse":43,"size":13202},"021654":{"edges":63,"n_sparse":20,"size":14662},"021656":{"edges":60,"n_sparse":60,"size":10698},"021658":{"edges":162,"n_sparse":132,"size":12651},"021660":{"edges":1568,"n_sparse":1139,"size":129189},"021664":{"edges":4,"n_sparse":4,"size":1447},"021667":{"edges":25,"n_sparse":13,"size":5880},"021669":{"edges":38,"n_sparse":38,"size":6799},"021670":{"edges":14,"n_sparse":14,"size":4336},"021671":{"edges":19,"n_sparse":16,"size":6065},"021673":{"edges":10,"n_sparse":9,"size":3412},"021674":{"edges":48,"n_sparse":27,"size":13958},"021676":{"edges":63,"n_sparse":44,"size":8500},"021678":{"edges":10,"n_sparse":10,"size":3084},"021687":{"edges":45,"n_sparse":40,"size":6459},"021688":{"edges":261,"n_sparse":206,"size":31416},"021689":{"edges":46,"n_sparse":45,"size":8629},"021695":{"edges":92,"n_sparse":81,"size":10802},"021697":{"edges":8,"n_sparse":6,"size":2095},"021700":{"edges":51,"n_sparse":49,"size":6737},"021704":{"edges":153,"n_sparse":139,"size":19875},"021706":{"edges":82,"n_sparse":36,"size":13367},"021710":{"edges":34,"n_sparse":31,"size":6214},"021711":{"edges":143,"n_sparse":143,"size":40804},"021713":{"edges":320,"n_sparse":251,"size":32285},"021720":{"edges":16,"n_sparse":10,"size":3115},"021721":{"edges":4,"n_sparse":3,"size":1441},"021729":{"edges":2205,"n_sparse":1815,"size":176791},"021730":{"edges":42,"n_sparse":42,"size":12556},"021731":{"edges":124,"n_sparse":36,"size":20551},"021737":{"edges":26,"n_sparse":26,"size":7290},"021738":{"edges":34,"n_sparse":17,"size":6357},"021742":{"edges":10,"n_sparse":10,"size":3477},"021743":{"edges":195,"n_sparse":154,"size":21286},"021744":{"edges":108,"n_sparse":30,"size":31624},"021746":{"edges":7,"n_sparse":6,"size":2209},"021748":{"edges":52,"n_sparse":1,"size":15318},"021752":{"edges":600,"n_sparse":566,"size":60485},"021753":{"edges":122,"n_sparse":122,"size":20857},"021756":{"edges":31,"n_sparse":31,"size":8997},"021758":{"edges":46,"n_sparse":46,"size":8630},"021762":{"edges":28,"n_sparse":28,"size":5254},"021770":{"edges":7,"n_sparse":7,"size":2387},"021773":{"edges":616,"n_sparse":569,"size":48485},"021774":{"edges":10,"n_sparse":10,"size":3265},"021775":{"edges":330,"n_sparse":243,"size":28542},"021777":{"edges":348,"n_sparse":206,"size":56611},"021778":{"edges":66,"n_sparse":64,"size":11600},"021782":{"edges":24,"n_sparse":13,"size":4850},"021785":{"edges":4,"n_sparse":4,"size":1527},"021789":{"edges":29,"n_sparse":6,"size":8804},"021794":{"edges":16,"n_sparse":3,"size":4906},"021802":{"edges":96,"n_sparse":94,"size":12757},"021810":{"edges":35,"n_sparse":35,"size":9044},"021812":{"edges":4,"n_sparse":4,"size":1412},"021814":{"edges":7,"n_sparse":7,"size":2412},"021817":{"edges":28,"n_sparse":27,"size":5242},"021821":{"edges":7,"n_sparse":7,"size":2349},"021823":{"edges":98,"n_sparse":95,"size":17564},"021825":{"edges":61,"n_sparse":49,"size":17214},"021829":{"edges":33,"n_sparse":33,"size":4780},"021830":{"edges":36,"n_sparse":25,"size":10450},"021835":{"edges":4,"n_sparse":4,"size":1523},"021839":{"edges":41,"n_sparse":41,"size":11667},"021840":{"edges":114,"n_sparse":57,"size":20030},"021842":{"edges":32,"n_sparse":32,"size":6440},"021844":{"edges":13,"n_sparse":13,"size":3959},"021849":{"edges":123,"n_sparse":64,"size":15964},"021850":{"edges":84,"n_sparse":48,"size":13979},"021852":{"edges":16,"n_sparse":12,"size":3171},"021856":{"edges":30,"n_sparse":29,"size":5683},"021858":{"edges":7,"n_sparse":6,"size":2269},"021861":{"edges":7,"n_sparse":7,"size":2306},"021862":{"edges":22,"n_sparse":22,"size":4151},"021864":{"edges":9,"n_sparse":5,"size":2585},"021866":{"edges":28,"n_sparse":16,"size":5159},"021868":{"edges":43,"n_sparse":41,"size":10644},"021871":{"edges":4,"n_sparse":0,"size":1440},"021875":{"edges":7,"n_sparse":7,"size":2469},"021876":{"edges":13,"n_sparse":12,"size":3732},"021877":{"edges":99,"n_sparse":90,"size":14036},"021879":{"edges":27,"n_sparse":8,"size":8309},"021880":{"edges":3762,"n_sparse":2785,"size":213633},"021882":{"edges":22,"n_sparse":18,"size":6659},"021883":{"edges":28,"n_sparse":28,"size":5068},"021884":{"edges":16,"n_sparse":16,"size":4816},"021892":{"edges":9,"n_sparse":8,"size":2859},"021896":{"edges":38,"n_sparse":38,"size":11481},"021897":{"edges":14,"n_sparse":13,"size":2954},"021902":{"edges":20,"n_sparse":15,"size":6385},"021903":{"edges":40,"n_sparse":20,"size":7585},"021906":{"edges":824,"n_sparse":816,"size":89943},"021908":{"edges":1020,"n_sparse":979,"size":64115},"021909":{"edges":184,"n_sparse":169,"size":20236},"021910":{"edges":59,"n_sparse":59,"size":17807},"021911":{"edges":4,"n_sparse":4,"size":1438},"021912":{"edges":141,"n_sparse":138,"size":39306},"021920":{"edges":30,"n_sparse":24,"size":4522},"021923":{"edges":295,"n_sparse":186,"size":30369},"021925":{"edges":19,"n_sparse":19,"size":6026},"021926":{"edges":218,"n_sparse":191,"size":36589},"021928":{"edges":21,"n_sparse":12,"size":6192},"021929":{"edges":539,"n_sparse":501,"size":45637},"021936":{"edges":13,"n_sparse":13,"size":4278},"021937":{"edges":489,"n_sparse":469,"size":65734},"021938":{"edges":80,"n_sparse":51,"size":9763},"021945":{"edges":31,"n_sparse":30,"size":9058},"021946":{"edges":10,"n_sparse":9,"size":3024},"021947":{"edges":158,"n_sparse":79,"size":27838},"021949":{"edges":4,"n_sparse":4,"size":1592},"021951":{"edges":4,"n_sparse":4,"size":1458},"021957":{"edges":468,"n_sparse":297,"size":52345},"021958":{"edges":16,"n_sparse":7,"size":2858},"021963":{"edges":31,"n_sparse":30,"size":9529},"021964":{"edges":58,"n_sparse":40,"size":16048},"021976":{"edges":678,"n_sparse":555,"size":58571},"021977":{"edges":273,"n_sparse":246,"size":36898},"021978":{"edges":15,"n_sparse":3,"size":4774},"021985":{"edges":4,"n_sparse":3,"size":1489},"021986":{"edges":180,"n_sparse":177,"size":23825},"021990":{"edges":11,"n_sparse":9,"size":3493},"021991":{"edges":212,"n_sparse":211,"size":35309},"021992":{"edges":68,"n_sparse":66,"size":11672},"021994":{"edges":11,"n_sparse":11,"size":3550},"021995":{"edges":1420,"n_sparse":1309,"size":97735},"021997":{"edges":23,"n_sparse":21,"size":7144},"021999":{"edges":4,"n_sparse":4,"size":1434},"022003":{"edges":27,"n_sparse":25,"size":8293},"022004":{"edges":22,"n_sparse":20,"size":4205},"022007":{"edges":23,"n_sparse":20,"size":6932},"022008":{"edges":4,"n_sparse":3,"size":1487},"022011":{"edges":782,"n_sparse":763,"size":122440},"022012":{"edges":108,"n_sparse":77,"size":14245},"022013":{"edges":11,"n_sparse":6,"size":3578},"022014":{"edges":36,"n_sparse":0,"size":6800},"022020":{"edges":23,"n_sparse":22,"size":7194},"022021":{"edges":72,"n_sparse":63,"size":9381},"022023":{"edges":100,"n_sparse":74,"size":17103},"022024":{"edges":93,"n_sparse":91,"size":12864},"022025":{"edges":4,"n_sparse":4,"size":1530},"022030":{"edges":68,"n_sparse":38,"size":18814},"022033":{"edges":51,"n_sparse":31,"size":14359},"022036":{"edges":125,"n_sparse":106,"size":36758},"022037":{"edges":19,"n_sparse":13,"size":5557},"022041":{"edges":1,"n_sparse":0,"size":622},"022044":{"edges":745,"n_sparse":676,"size":70659},"022047":{"edges":33,"n_sparse":15,"size":4666},"022048":{"edges":24,"n_sparse":15,"size":3821},"022051":{"edges":333,"n_sparse":324,"size":40921},"022055":{"edges":32,"n_sparse":31,"size":9838},"022056":{"edges":44,"n_sparse":27,"size":8052},"022057":{"edges":42,"n_sparse":42,"size":8129},"022058":{"edges":10,"n_sparse":10,"size":3236},"022059":{"edges":56,"n_sparse":54,"size":10441},"022063":{"edges":21,"n_sparse":20,"size":5955},"022064":{"edges":13,"n_sparse":13,"size":4077},"022065":{"edges":1572,"n_sparse":1517,"size":132091},"022067":{"edges":8,"n_sparse":6,"size":1795},"022068":{"edges":88,"n_sparse":84,"size":10802},"022074":{"edges":9,"n_sparse":7,"size":2931},"022075":{"edges":8,"n_sparse":8,"size":2834},"022078":{"edges":584,"n_sparse":580,"size":44285},"022081":{"edges":145,"n_sparse":133,"size":14952},"022083":{"edges":14,"n_sparse":13,"size":4379},"022088":{"edges":14,"n_sparse":14,"size":2951},"022090":{"edges":13,"n_sparse":6,"size":4079},"022100":{"edges":4,"n_sparse":3,"size":1445},"022101":{"edges":56,"n_sparse":34,"size":16458},"022103":{"edges":28,"n_sparse":28,"size":8585},"022104":{"edges":46,"n_sparse":22,"size":8411},"022106":{"edges":4,"n_sparse":3,"size":1465},"022107":{"edges":4,"n_sparse":3,"size":1484},"022108":{"edges":4,"n_sparse":4,"size":1391},"022110":{"edges":84,"n_sparse":78,"size":10872},"022114":{"edges":26,"n_sparse":0,"size":5166},"022116":{"edges":6,"n_sparse":6,"size":1791},"022117":{"edges":88,"n_sparse":83,"size":9344},"022118":{"edges":22,"n_sparse":22,"size":4510},"022127":{"edges":41,"n_sparse":36,"size":12276},"022128":{"edges":30,"n_sparse":28,"size":8916},"022129":{"edges":25,"n_sparse":25,"size":7585},"022134":{"edges":34,"n_sparse":34,"size":6222},"022145":{"edges":81,"n_sparse":61,"size":11121},"022150":{"edges":19,"n_sparse":18,"size":5808},"022154":{"edges":366,"n_sparse":357,"size":99596},"022156":{"edges":8,"n_sparse":7,"size":2731},"022157":{"edges":13,"n_sparse":13,"size":4072},"022159":{"edges":18,"n_sparse":18,"size":5220},"022161":{"edges":560,"n_sparse":475,"size":51626},"022165":{"edges":80,"n_sparse":69,"size":22369},"022173":{"edges":16,"n_sparse":13,"size":3123},"022180":{"edges":4,"n_sparse":4,"size":1484},"022181":{"edges":144,"n_sparse":144,"size":17638},"022184":{"edges":776,"n_sparse":737,"size":64550},"022185":{"edges":24,"n_sparse":18,"size":3722},"022187":{"edges":104,"n_sparse":104,"size":13200},"022192":{"edges":515,"n_sparse":455,"size":51537},"022193":{"edges":11,"n_sparse":11,"size":3617},"022196":{"edges":8,"n_sparse":3,"size":2688},"022198":{"edges":7,"n_sparse":7,"size":2429},"022200":{"edges":5382,"n_sparse":5148,"size":312085},"022201":{"edges":189,"n_sparse":162,"size":25079},"022202":{"edges":168,"n_sparse":161,"size":20293},"022203":{"edges":4,"n_sparse":4,"size":1532},"022204":{"edges":117,"n_sparse":107,"size":16138},"022205":{"edges":47,"n_sparse":28,"size":13900},"022206":{"edges":50,"n_sparse":45,"size":15308},"022210":{"edges":16,"n_sparse":15,"size":4761},"022217":{"edges":8,"n_sparse":6,"size":2676},"022219":{"edges":10,"n_sparse":10,"size":3402},"022221":{"edges":5,"n_sparse":5,"size":1682},"022225":{"edges":62,"n_sparse":40,"size":10957},"022231":{"edges":9,"n_sparse":9,"size":2790},"022233":{"edges":7,"n_sparse":6,"size":2331},"022244":{"edges":16,"n_sparse":9,"size":4603},"022247":{"edges":84,"n_sparse":34,"size":14279},"022249":{"edges":176,"n_sparse":131,"size":20488},"022250":{"edges":81,"n_sparse":72,"size":23909},"022251":{"edges":8,"n_sparse":8,"size":2762},"022252":{"edges":124,"n_sparse":60,"size":13982},"022253":{"edges":203,"n_sparse":198,"size":17937},"022254":{"edges":174,"n_sparse":173,"size":16691},"022255":{"edges":203,"n_sparse":198,"size":17927},"022256":{"edges":52,"n_sparse":43,"size":8633},"022257":{"edges":8,"n_sparse":8,"size":1902},"022262":{"edges":44,"n_sparse":0,"size":12977},"022264":{"edges":148,"n_sparse":141,"size":18013},"022266":{"edges":19,"n_sparse":4,"size":5941},"022268":{"edges":4,"n_sparse":4,"size":1532},"022271":{"edges":1521,"n_sparse":1389,"size":110599},"022272":{"edges":348,"n_sparse":345,"size":44621},"022273":{"edges":1,"n_sparse":0,"size":666},"022275":{"edges":4,"n_sparse":0,"size":1478},"022277":{"edges":18,"n_sparse":15,"size":5472},"022278":{"edges":16,"n_sparse":15,"size":3231},"022281":{"edges":32,"n_sparse":0,"size":8285},"022283":{"edges":8,"n_sparse":0,"size":2519},"022287":{"edges":408,"n_sparse":347,"size":33437},"022291":{"edges":1432,"n_sparse":1100,"size":118097},"022292":{"edges":7,"n_sparse":7,"size":2397},"022301":{"edges":32,"n_sparse":32,"size":6005},"022304":{"edges":105,"n_sparse":51,"size":28615},"022306":{"edges":156,"n_sparse":156,"size":18633},"022307":{"edges":106,"n_sparse":104,"size":18529},"022308":{"edges":34,"n_sparse":33,"size":9998},"022309":{"edges":31,"n_sparse":31,"size":9480},"022311":{"edges":14,"n_sparse":14,"size":4841},"022314":{"edges":11,"n_sparse":9,"size":3483},"022315":{"edges":864,"n_sparse":694,"size":68802},"022318":{"edges":41,"n_sparse":36,"size":12271},"022320":{"edges":40,"n_sparse":40,"size":7431},"022321":{"edges":210,"n_sparse":209,"size":19675},"022328":{"edges":34,"n_sparse":32,"size":6403},"022332":{"edges":7,"n_sparse":3,"size":2320},"022334":{"edges":64,"n_sparse":56,"size":8238},"022341":{"edges":48,"n_sparse":47,"size":8687},"022348":{"edges":640,"n_sparse":639,"size":54679},"022350":{"edges":34,"n_sparse":32,"size":6340},"022352":{"edges":630,"n_sparse":620,"size":63872},"022362":{"edges":120,"n_sparse":63,"size":20552},"022363":{"edges":18,"n_sparse":18,"size":5599},"022368":{"edges":7,"n_sparse":7,"size":2406},"022369":{"edges":1152,"n_sparse":1067,"size":83956},"022370":{"edges":4,"n_sparse":4,"size":1442},"022371":{"edges":4,"n_sparse":4,"size":1402},"022372":{"edges":10,"n_sparse":10,"size":3269},"022377":{"edges":4,"n_sparse":0,"size":1571},"022382":{"edges":40,"n_sparse":40,"size":7152},"022383":{"edges":33,"n_sparse":29,"size":9766},"022386":{"edges":4,"n_sparse":4,"size":1405},"022387":{"edges":152,"n_sparse":145,"size":17526},"022395":{"edges":8,"n_sparse":8,"size":2740},"022396":{"edges":4,"n_sparse":4,"size":1448},"022399":{"edges":174,"n_sparse":145,"size":28179},"022401":{"edges":4,"n_sparse":3,"size":1366},"022404":{"edges":23,"n_sparse":19,"size":6888},"022405":{"edges":4,"n_sparse":4,"size":1577},"022406":{"edges":1375,"n_sparse":1311,"size":93658},"022408":{"edges":123,"n_sparse":111,"size":16467},"022410":{"edges":42,"n_sparse":35,"size":6292},"022411":{"edges":7,"n_sparse":6,"size":2128},"022416":{"edges":472,"n_sparse":448,"size":39481},"022417":{"edges":103,"n_sparse":102,"size":29233},"022418":{"edges":96,"n_sparse":81,"size":11984},"022421":{"edges":4,"n_sparse":3,"size":1406},"022425":{"edges":427,"n_sparse":345,"size":38373},"022426":{"edges":2895,"n_sparse":2712,"size":178131},"022428":{"edges":24,"n_sparse":20,"size":7259},"022430":{"edges":61,"n_sparse":54,"size":16873},"022433":{"edges":1690,"n_sparse":1610,"size":107272},"022434":{"edges":28,"n_sparse":23,"size":4935},"022436":{"edges":34,"n_sparse":34,"size":6607},"022445":{"edges":24,"n_sparse":24,"size":4460},"022450":{"edges":170,"n_sparse":170,"size":17885},"022456":{"edges":82,"n_sparse":47,"size":13570},"022458":{"edges":14,"n_sparse":14,"size":2667},"022460":{"edges":28,"n_sparse":26,"size":5673},"022468":{"edges":66,"n_sparse":66,"size":12018},"022472":{"edges":2304,"n_sparse":2173,"size":136006},"022474":{"edges":100,"n_sparse":100,"size":11883},"022483":{"edges":156,"n_sparse":116,"size":21328},"022484":{"edges":16,"n_sparse":16,"size":5268},"022488":{"edges":75,"n_sparse":52,"size":8166},"022496":{"edges":1860,"n_sparse":1775,"size":135961},"022501":{"edges":11,"n_sparse":11,"size":3677},"022502":{"edges":27,"n_sparse":24,"size":8019},"022504":{"edges":315,"n_sparse":306,"size":31771},"022505":{"edges":67,"n_sparse":47,"size":18394},"022510":{"edges":24,"n_sparse":19,"size":7344},"022511":{"edges":660,"n_sparse":520,"size":65655},"022512":{"edges":33,"n_sparse":26,"size":4765},"022517":{"edges":150,"n_sparse":143,"size":26968},"022518":{"edges":68,"n_sparse":64,"size":20229},"022519":{"edges":35,"n_sparse":29,"size":9191},"022522":{"edges":42,"n_sparse":41,"size":12697},"022523":{"edges":12,"n_sparse":11,"size":3569},"022525":{"edges":47,"n_sparse":47,"size":14216},"022526":{"edges":18,"n_sparse":18,"size":5703},"022527":{"edges":180,"n_sparse":134,"size":20876},"022529":{"edges":3276,"n_sparse":2909,"size":202011},"022532":{"edges":295,"n_sparse":260,"size":28384},"022535":{"edges":2190,"n_sparse":2102,"size":154734},"022544":{"edges":31,"n_sparse":31,"size":9553},"022545":{"edges":4,"n_sparse":3,"size":1459},"022549":{"edges":10,"n_sparse":10,"size":3308},"022554":{"edges":720,"n_sparse":547,"size":60434},"022555":{"edges":92,"n_sparse":58,"size":16102},"022560":{"edges":46,"n_sparse":42,"size":13400},"022561":{"edges":240,"n_sparse":240,"size":26306},"022563":{"edges":54,"n_sparse":51,"size":7709},"022567":{"edges":12,"n_sparse":12,"size":3905},"022568":{"edges":4,"n_sparse":3,"size":1427},"022569":{"edges":58,"n_sparse":46,"size":10062},"022571":{"edges":11,"n_sparse":11,"size":3658},"022572":{"edges":8,"n_sparse":8,"size":2806},"022573":{"edges":11,"n_sparse":11,"size":3598},"022574":{"edges":118,"n_sparse":85,"size":18513},"022577":{"edges":65,"n_sparse":51,"size":7392},"022580":{"edges":219,"n_sparse":219,"size":29615},"022581":{"edges":12,"n_sparse":11,"size":3944},"050444":{"edges":13,"n_sparse":13,"size":4039},"050587":{"edges":4,"n_sparse":3,"size":1439},"050592":{"edges":4,"n_sparse":4,"size":1364},"050616":{"edges":4,"n_sparse":4,"size":1364},"050628":{"edges":4,"n_sparse":4,"size":1364},"050630":{"edges":4,"n_sparse":3,"size":1439},"050684":{"edges":20,"n_sparse":19,"size":6137},"050685":{"edges":8,"n_sparse":6,"size":1627},"050686":{"edges":22,"n_sparse":19,"size":4289},"050703":{"edges":4,"n_sparse":4,"size":1533},"050706":{"edges":4,"n_sparse":3,"size":1326},"050715":{"edges":109,"n_sparse":109,"size":32245},"050716":{"edges":109,"n_sparse":109,"size":32245},"050718":{"edges":87,"n_sparse":0,"size":11721},"050740":{"edges":17,"n_sparse":16,"size":4704},"050746":{"edges":22,"n_sparse":22,"size":4253},"050750":{"edges":20,"n_sparse":19,"size":6144},"050753":{"edges":7,"n_sparse":7,"size":2345},"050757":{"edges":4,"n_sparse":4,"size":1490},"050775":{"edges":9,"n_sparse":7,"size":3062},"050777":{"edges":10,"n_sparse":10,"size":3168},"050782":{"edges":13,"n_sparse":13,"size":3869},"050785":{"edges":32,"n_sparse":32,"size":9779},"050786":{"edges":72,"n_sparse":72,"size":10246},"050790":{"edges":132,"n_sparse":128,"size":17262},"050791":{"edges":8,"n_sparse":6,"size":2724},"050793":{"edges":21,"n_sparse":15,"size":6438},"050795":{"edges":18,"n_sparse":18,"size":5052},"050797":{"edges":7,"n_sparse":6,"size":2281},"050801":{"edges":4,"n_sparse":0,"size":1494},"050802":{"edges":26,"n_sparse":26,"size":4380},"050804":{"edges":11,"n_sparse":10,"size":3681},"050805":{"edges":190,"n_sparse":152,"size":33145},"050808":{"edges":150,"n_sparse":130,"size":20603},"050810":{"edges":43,"n_sparse":26,"size":11525},"050813":{"edges":778,"n_sparse":778,"size":112326},"050814":{"edges":70,"n_sparse":60,"size":12483},"050818":{"edges":42,"n_sparse":41,"size":7588},"050819":{"edges":342,"n_sparse":308,"size":32993},"072303":{"edges":12,"n_sparse":4,"size":1788},"072304":{"edges":12,"n_sparse":4,"size":1788},"200045":{"edges":4,"n_sparse":3,"size":1469},"200063":{"edges":996,"n_sparse":816,"size":96015},"200153":{"edges":17,"n_sparse":17,"size":5416},"200175":{"edges":4,"n_sparse":3,"size":1424},"200179":{"edges":8,"n_sparse":7,"size":2365},"200327":{"edges":48,"n_sparse":44,"size":7914},"200533":{"edges":635,"n_sparse":442,"size":62646},"200603":{"edges":330,"n_sparse":254,"size":32295},"200678":{"edges":34,"n_sparse":32,"size":6371},"200796":{"edges":34,"n_sparse":30,"size":10499},"201023":{"edges":130,"n_sparse":106,"size":14177},"201110":{"edges":17,"n_sparse":17,"size":5430},"201152":{"edges":22,"n_sparse":22,"size":4099},"201277":{"edges":1,"n_sparse":0,"size":627},"201280":{"edges":3240,"n_sparse":3123,"size":221052},"201281":{"edges":1428,"n_sparse":1395,"size":126472},"201292":{"edges":28,"n_sparse":17,"size":5205},"201367":{"edges":4,"n_sparse":4,"size":1438},"201373":{"edges":31,"n_sparse":31,"size":9116},"201444":{"edges":120,"n_sparse":101,"size":12742},"201532":{"edges":16,"n_sparse":12,"size":3148},"201635":{"edges":255,"n_sparse":113,"size":34939},"201655":{"edges":9,"n_sparse":9,"size":2841},"201656":{"edges":93,"n_sparse":93,"size":13064},"201688":{"edges":72,"n_sparse":39,"size":20464},"201699":{"edges":22,"n_sparse":17,"size":4343},"201739":{"edges":40,"n_sparse":22,"size":5363},"201820":{"edges":4,"n_sparse":3,"size":1484},"201848":{"edges":93,"n_sparse":92,"size":12308},"201917":{"edges":20,"n_sparse":20,"size":5960},"201922":{"edges":126,"n_sparse":116,"size":16939},"201923":{"edges":42,"n_sparse":4,"size":11621},"202008":{"edges":7,"n_sparse":7,"size":2538},"202020":{"edges":240,"n_sparse":240,"size":24568},"202022":{"edges":35,"n_sparse":35,"size":5357},"202057":{"edges":15480,"n_sparse":15479,"size":957611},"202088":{"edges":1,"n_sparse":1,"size":778},"202091":{"edges":7,"n_sparse":6,"size":2297},"202100":{"edges":66,"n_sparse":65,"size":9480},"202107":{"edges":168,"n_sparse":152,"size":47390},"202123":{"edges":105,"n_sparse":95,"size":28926},"202129":{"edges":22,"n_sparse":22,"size":4120},"202155":{"edges":1125,"n_sparse":1044,"size":93455},"202192":{"edges":408,"n_sparse":395,"size":35811},"202211":{"edges":58,"n_sparse":31,"size":16033},"202236":{"edges":85,"n_sparse":67,"size":9537},"202258":{"edges":174,"n_sparse":173,"size":29301},"202270":{"edges":426,"n_sparse":380,"size":53353},"202276":{"edges":10,"n_sparse":9,"size":3196},"202278":{"edges":122,"n_sparse":116,"size":19328},"202292":{"edges":43,"n_sparse":39,"size":11966},"202293":{"edges":1088,"n_sparse":1062,"size":93562},"202317":{"edges":8,"n_sparse":8,"size":2837},"202324":{"edges":99,"n_sparse":93,"size":13640},"202331":{"edges":28,"n_sparse":26,"size":8740},"202343":{"edges":876,"n_sparse":829,"size":75130},"202379":{"edges":40,"n_sparse":36,"size":5258},"202428":{"edges":11,"n_sparse":9,"size":3355},"202429":{"edges":14,"n_sparse":12,"size":3035},"202439":{"edges":26,"n_sparse":26,"size":4651},"202450":{"edges":190,"n_sparse":168,"size":18960},"202497":{"edges":14,"n_sparse":14,"size":4595},"202513":{"edges":17,"n_sparse":17,"size":5380},"202514":{"edges":17,"n_sparse":17,"size":5245},"202570":{"edges":16,"n_sparse":16,"size":2889},"202611":{"edges":250,"n_sparse":247,"size":26015},"202714":{"edges":372,"n_sparse":360,"size":36238},"202736":{"edges":4,"n_sparse":4,"size":1446},"202788":{"edges":22,"n_sparse":17,"size":6388},"202799":{"edges":46,"n_sparse":46,"size":13811},"202806":{"edges":660,"n_sparse":533,"size":52653},"202810":{"edges":36,"n_sparse":36,"size":5343},"202811":{"edges":732,"n_sparse":708,"size":79776},"202833":{"edges":585,"n_sparse":303,"size":53080},"202834":{"edges":20,"n_sparse":16,"size":3254},"202860":{"edges":160,"n_sparse":159,"size":27559},"202880":{"edges":286,"n_sparse":242,"size":49638},"202895":{"edges":182,"n_sparse":161,"size":30481},"202971":{"edges":882,"n_sparse":676,"size":76833},"202992":{"edges":42,"n_sparse":41,"size":7993},"203045":{"edges":16,"n_sparse":13,"size":5002},"203085":{"edges":30,"n_sparse":29,"size":9171},"203093":{"edges":35,"n_sparse":32,"size":9436},"203094":{"edges":4,"n_sparse":4,"size":1516},"203100":{"edges":268,"n_sparse":255,"size":45509},"203108":{"edges":56,"n_sparse":53,"size":16707},"203137":{"edges":44,"n_sparse":0,"size":12711},"203159":{"edges":45,"n_sparse":45,"size":7016},"203168":{"edges":100,"n_sparse":100,"size":12270},"203188":{"edges":130,"n_sparse":130,"size":14861},"203214":{"edges":58,"n_sparse":50,"size":10363},"203255":{"edges":16,"n_sparse":14,"size":3101},"203284":{"edges":537,"n_sparse":413,"size":67736},"203312":{"edges":786,"n_sparse":628,"size":74148},"203313":{"edges":5,"n_sparse":5,"size":1815},"203340":{"edges":22,"n_sparse":22,"size":7013},"203341":{"edges":126,"n_sparse":115,"size":13181},"203388":{"edges":46,"n_sparse":17,"size":7534},"203389":{"edges":131,"n_sparse":119,"size":35380},"203414":{"edges":2646,"n_sparse":2463,"size":165921},"203415":{"edges":160,"n_sparse":158,"size":15927},"203441":{"edges":262,"n_sparse":252,"size":44978},"203469":{"edges":444,"n_sparse":425,"size":43078},"203491":{"edges":4,"n_sparse":4,"size":1422},"203496":{"edges":152,"n_sparse":152,"size":17816},"203505":{"edges":165,"n_sparse":141,"size":22984},"203510":{"edges":5,"n_sparse":3,"size":1770},"203565":{"edges":1458,"n_sparse":1458,"size":100456},"203567":{"edges":232,"n_sparse":222,"size":27778},"203568":{"edges":13,"n_sparse":13,"size":4268},"203585":{"edges":111,"n_sparse":92,"size":14321},"203634":{"edges":65,"n_sparse":60,"size":18281},"203667":{"edges":11,"n_sparse":0,"size":3489},"203684":{"edges":24,"n_sparse":19,"size":3900},"203697":{"edges":64,"n_sparse":34,"size":7386},"203752":{"edges":7,"n_sparse":7,"size":2496},"203756":{"edges":21,"n_sparse":9,"size":6723},"203791":{"edges":24,"n_sparse":3,"size":6517},"203794":{"edges":105,"n_sparse":54,"size":28788},"203858":{"edges":500,"n_sparse":494,"size":55537},"203922":{"edges":8,"n_sparse":8,"size":1905},"203923":{"edges":64,"n_sparse":57,"size":8436},"203971":{"edges":8,"n_sparse":7,"size":1851},"203975":{"edges":132,"n_sparse":107,"size":23006},"203985":{"edges":8,"n_sparse":6,"size":2023},"204026":{"edges":460,"n_sparse":277,"size":49964},"204031":{"edges":116,"n_sparse":112,"size":19546},"204042":{"edges":198,"n_sparse":196,"size":18437},"204061":{"edges":5,"n_sparse":0,"size":1662},"204063":{"edges":288,"n_sparse":278,"size":38983},"204096":{"edges":8,"n_sparse":6,"size":2670},"204114":{"edges":342,"n_sparse":280,"size":30090},"204141":{"edges":12,"n_sparse":11,"size":3737},"204153":{"edges":11,"n_sparse":7,"size":3233},"204168":{"edges":19,"n_sparse":19,"size":5860},"204200":{"edges":20,"n_sparse":13,"size":3787},"204223":{"edges":26,"n_sparse":26,"size":4881},"204242":{"edges":148,"n_sparse":145,"size":17112},"204251":{"edges":4,"n_sparse":4,"size":1312},"204275":{"edges":1148,"n_sparse":1100,"size":101268},"204286":{"edges":4,"n_sparse":4,"size":1455},"204308":{"edges":130,"n_sparse":125,"size":14019},"204353":{"edges":54,"n_sparse":53,"size":8121},"204370":{"edges":200,"n_sparse":174,"size":20578},"204384":{"edges":8,"n_sparse":6,"size":2662},"204399":{"edges":12,"n_sparse":10,"size":3912},"204410":{"edges":156,"n_sparse":153,"size":20565},"204412":{"edges":26,"n_sparse":25,"size":7684},"204426":{"edges":4,"n_sparse":0,"size":1405},"204427":{"edges":100,"n_sparse":100,"size":12148},"204441":{"edges":11,"n_sparse":7,"size":3472},"204442":{"edges":4,"n_sparse":4,"size":1457},"204447":{"edges":255,"n_sparse":243,"size":27425},"204485":{"edges":76,"n_sparse":76,"size":21995},"204516":{"edges":15,"n_sparse":15,"size":4785},"204569":{"edges":10,"n_sparse":9,"size":3172},"204592":{"edges":21,"n_sparse":18,"size":6400},"204623":{"edges":834,"n_sparse":821,"size":79095},"204629":{"edges":1728,"n_sparse":1728,"size":132615},"204640":{"edges":10,"n_sparse":10,"size":3239},"204654":{"edges":18,"n_sparse":0,"size":5553},"204655":{"edges":168,"n_sparse":154,"size":20942},"204671":{"edges":160,"n_sparse":150,"size":27001},"204677":{"edges":5,"n_sparse":4,"size":2009},"204708":{"edges":62,"n_sparse":61,"size":17835},"204734":{"edges":7,"n_sparse":4,"size":1991},"204760":{"edges":19,"n_sparse":17,"size":6057},"204768":{"edges":7,"n_sparse":6,"size":2294},"204803":{"edges":44,"n_sparse":44,"size":7083},"204819":{"edges":58,"n_sparse":55,"size":10709},"204820":{"edges":77,"n_sparse":77,"size":21389},"204824":{"edges":42,"n_sparse":13,"size":12391},"204886":{"edges":370,"n_sparse":303,"size":60483},"204958":{"edges":336,"n_sparse":336,"size":38183},"205003":{"edges":8,"n_sparse":6,"size":2649},"205029":{"edges":108,"n_sparse":90,"size":13524},"205053":{"edges":20,"n_sparse":18,"size":6170},"205060":{"edges":64,"n_sparse":58,"size":11148},"205065":{"edges":87,"n_sparse":87,"size":12656},"205098":{"edges":180,"n_sparse":177,"size":23672},"205103":{"edges":114,"n_sparse":102,"size":19632},"205108":{"edges":54,"n_sparse":54,"size":10194},"205109":{"edges":12,"n_sparse":4,"size":3736},"205122":{"edges":9,"n_sparse":0,"size":2502},"205123":{"edges":40,"n_sparse":34,"size":10923},"205175":{"edges":10,"n_sparse":10,"size":2876},"205223":{"edges":38,"n_sparse":37,"size":7231},"205266":{"edges":7,"n_sparse":3,"size":2080},"205353":{"edges":18,"n_sparse":14,"size":5606},"205382":{"edges":31,"n_sparse":28,"size":9162},"205388":{"edges":11,"n_sparse":11,"size":3622},"205395":{"edges":123,"n_sparse":108,"size":16056},"205410":{"edges":28,"n_sparse":28,"size":5229},"205422":{"edges":63,"n_sparse":51,"size":8053},"205435":{"edges":62,"n_sparse":42,"size":10242},"205436":{"edges":62,"n_sparse":42,"size":10242},"205437":{"edges":1573,"n_sparse":1442,"size":111391},"205474":{"edges":12,"n_sparse":12,"size":4104},"205488":{"edges":76,"n_sparse":76,"size":13900},"205489":{"edges":8,"n_sparse":8,"size":2662},"205494":{"edges":315,"n_sparse":254,"size":32592},"205551":{"edges":14,"n_sparse":14,"size":4317},"205552":{"edges":3344,"n_sparse":2947,"size":221750},"205579":{"edges":17,"n_sparse":16,"size":5085},"205580":{"edges":123,"n_sparse":87,"size":16183},"205596":{"edges":160,"n_sparse":141,"size":18663},"205598":{"edges":20,"n_sparse":19,"size":6076},"205625":{"edges":200,"n_sparse":192,"size":34955},"205637":{"edges":44,"n_sparse":6,"size":8140},"205641":{"edges":51,"n_sparse":48,"size":15148},"205649":{"edges":134,"n_sparse":132,"size":23516},"205677":{"edges":3906,"n_sparse":3804,"size":261785},"205718":{"edges":264,"n_sparse":257,"size":34964},"205739":{"edges":104,"n_sparse":100,"size":30596},"205747":{"edges":52,"n_sparse":48,"size":7320},"205755":{"edges":17,"n_sparse":17,"size":5270},"205776":{"edges":4,"n_sparse":4,"size":1478},"205777":{"edges":192,"n_sparse":192,"size":24114},"205786":{"edges":12,"n_sparse":10,"size":3875},"205787":{"edges":100,"n_sparse":70,"size":11446},"205831":{"edges":8,"n_sparse":7,"size":2573},"205832":{"edges":22,"n_sparse":21,"size":4246},"205834":{"edges":318,"n_sparse":292,"size":41211},"205836":{"edges":36,"n_sparse":35,"size":6685},"205837":{"edges":36,"n_sparse":35,"size":6981},"205838":{"edges":36,"n_sparse":35,"size":6685},"205858":{"edges":609,"n_sparse":469,"size":52266},"205874":{"edges":230,"n_sparse":152,"size":40201},"205879":{"edges":54,"n_sparse":53,"size":8111},"205934":{"edges":135,"n_sparse":103,"size":12914},"206030":{"edges":60,"n_sparse":60,"size":8207},"206038":{"edges":1335,"n_sparse":1321,"size":98569},"206073":{"edges":3350,"n_sparse":3260,"size":257904},"206089":{"edges":120,"n_sparse":117,"size":16256},"206099":{"edges":770,"n_sparse":605,"size":77654},"206111":{"edges":656,"n_sparse":656,"size":57938},"206143":{"edges":22,"n_sparse":22,"size":7084},"206162":{"edges":17,"n_sparse":16,"size":4991},"206185":{"edges":4,"n_sparse":4,"size":1509},"206192":{"edges":104,"n_sparse":71,"size":18064},"206229":{"edges":9,"n_sparse":0,"size":2842},"206255":{"edges":85,"n_sparse":85,"size":25567},"206256":{"edges":61,"n_sparse":36,"size":14918},"206276":{"edges":7,"n_sparse":7,"size":2369},"206302":{"edges":10,"n_sparse":10,"size":3163},"206307":{"edges":16,"n_sparse":10,"size":4917},"206317":{"edges":19,"n_sparse":19,"size":5941},"206321":{"edges":48,"n_sparse":45,"size":8557},"206323":{"edges":20,"n_sparse":13,"size":5853},"206333":{"edges":112,"n_sparse":107,"size":20191},"206334":{"edges":32,"n_sparse":30,"size":6001},"206352":{"edges":4,"n_sparse":3,"size":1438},"206353":{"edges":16,"n_sparse":14,"size":3141},"206356":{"edges":4,"n_sparse":4,"size":1552},"206406":{"edges":447,"n_sparse":418,"size":60802},"206426":{"edges":24,"n_sparse":24,"size":3883},"206439":{"edges":64,"n_sparse":64,"size":19311},"206488":{"edges":816,"n_sparse":816,"size":70294},"206494":{"edges":55,"n_sparse":53,"size":6724},"206500":{"edges":44,"n_sparse":36,"size":12897},"206510":{"edges":12,"n_sparse":11,"size":3889},"206538":{"edges":81,"n_sparse":67,"size":10563},"206545":{"edges":104,"n_sparse":80,"size":18263},"206619":{"edges":980,"n_sparse":868,"size":86708},"206627":{"edges":372,"n_sparse":372,"size":59878},"206756":{"edges":128,"n_sparse":124,"size":22596},"206829":{"edges":1005,"n_sparse":958,"size":74124},"206843":{"edges":38,"n_sparse":34,"size":6973},"206910":{"edges":22,"n_sparse":18,"size":6607},"206911":{"edges":62,"n_sparse":62,"size":17949},"206940":{"edges":268,"n_sparse":219,"size":31503},"206947":{"edges":104,"n_sparse":80,"size":12706},"206966":{"edges":22,"n_sparse":21,"size":7162},"206976":{"edges":12,"n_sparse":12,"size":3970},"206977":{"edges":10,"n_sparse":10,"size":2271},"206995":{"edges":4,"n_sparse":4,"size":1606},"207027":{"edges":400,"n_sparse":286,"size":45978},"207071":{"edges":50,"n_sparse":50,"size":8916},"207078":{"edges":52,"n_sparse":41,"size":15352},"207103":{"edges":12,"n_sparse":12,"size":2557},"207145":{"edges":63,"n_sparse":63,"size":18493},"207154":{"edges":46,"n_sparse":26,"size":8019},"207155":{"edges":13,"n_sparse":13,"size":4179},"207202":{"edges":2324,"n_sparse":1258,"size":202496},"207233":{"edges":20,"n_sparse":20,"size":3929},"207318":{"edges":325,"n_sparse":250,"size":33536},"207356":{"edges":328,"n_sparse":324,"size":37707},"207533":{"edges":644,"n_sparse":580,"size":70806},"207534":{"edges":4,"n_sparse":4,"size":1475},"207561":{"edges":246,"n_sparse":230,"size":41847},"207589":{"edges":44,"n_sparse":32,"size":7958},"207620":{"edges":90,"n_sparse":90,"size":13002},"207621":{"edges":7,"n_sparse":7,"size":2265},"207695":{"edges":54,"n_sparse":43,"size":15585},"207793":{"edges":819,"n_sparse":786,"size":73583},"207795":{"edges":19,"n_sparse":17,"size":6164},"207865":{"edges":26,"n_sparse":12,"size":7476},"207916":{"edges":8,"n_sparse":8,"size":2711},"207917":{"edges":58,"n_sparse":54,"size":17512},"207920":{"edges":78,"n_sparse":78,"size":9887},"207923":{"edges":8,"n_sparse":8,"size":2757},"207924":{"edges":201,"n_sparse":115,"size":26805},"207925":{"edges":912,"n_sparse":881,"size":66543},"207930":{"edges":55,"n_sparse":48,"size":16255},"207931":{"edges":168,"n_sparse":146,"size":22568},"207932":{"edges":64,"n_sparse":54,"size":11673},"207946":{"edges":240,"n_sparse":208,"size":23581},"207947":{"edges":280,"n_sparse":265,"size":28406},"207958":{"edges":42,"n_sparse":42,"size":6225},"207960":{"edges":69,"n_sparse":69,"size":10403},"207962":{"edges":15,"n_sparse":14,"size":4817},"207981":{"edges":525,"n_sparse":491,"size":48786},"207986":{"edges":66,"n_sparse":65,"size":9713},"207988":{"edges":384,"n_sparse":384,"size":35501},"207997":{"edges":30,"n_sparse":30,"size":5908},"207999":{"edges":44,"n_sparse":44,"size":8314},"208010":{"edges":1428,"n_sparse":1428,"size":100517},"208026":{"edges":2583,"n_sparse":2496,"size":197172},"208030":{"edges":130,"n_sparse":107,"size":21373},"208032":{"edges":33,"n_sparse":33,"size":9386},"208051":{"edges":267,"n_sparse":243,"size":35996},"208054":{"edges":126,"n_sparse":121,"size":22233},"208056":{"edges":60,"n_sparse":57,"size":10710},"208065":{"edges":135,"n_sparse":134,"size":15542},"208073":{"edges":112,"n_sparse":102,"size":19872},"208078":{"edges":44,"n_sparse":44,"size":13312},"208079":{"edges":46,"n_sparse":36,"size":13958},"208081":{"edges":28,"n_sparse":20,"size":5326},"208082":{"edges":126,"n_sparse":88,"size":16567},"208088":{"edges":345,"n_sparse":345,"size":46372},"208090":{"edges":59,"n_sparse":57,"size":16989},"208114":{"edges":4,"n_sparse":4,"size":1648},"208144":{"edges":28,"n_sparse":28,"size":8294},"208147":{"edges":7,"n_sparse":6,"size":2329},"208159":{"edges":17,"n_sparse":17,"size":5231},"208171":{"edges":22,"n_sparse":22,"size":4672},"208183":{"edges":7,"n_sparse":7,"size":2331},"208193":{"edges":4,"n_sparse":4,"size":1444},"208194":{"edges":384,"n_sparse":312,"size":43943},"208215":{"edges":189,"n_sparse":153,"size":25239},"208219":{"edges":8,"n_sparse":8,"size":2650},"208223":{"edges":13,"n_sparse":11,"size":4079},"208224":{"edges":45,"n_sparse":45,"size":7010},"208232":{"edges":192,"n_sparse":190,"size":26459},"208246":{"edges":190,"n_sparse":171,"size":20202},"208251":{"edges":4,"n_sparse":3,"size":1466},"208254":{"edges":121,"n_sparse":75,"size":33142},"208259":{"edges":125,"n_sparse":78,"size":34332},"208261":{"edges":32,"n_sparse":32,"size":8675},"208271":{"edges":48,"n_sparse":39,"size":12977},"208276":{"edges":4,"n_sparse":4,"size":1629},"208277":{"edges":20,"n_sparse":16,"size":3234},"208288":{"edges":10,"n_sparse":9,"size":3097},"208294":{"edges":102,"n_sparse":96,"size":17778},"208325":{"edges":21,"n_sparse":20,"size":6327},"208341":{"edges":106,"n_sparse":96,"size":30139},"208351":{"edges":70,"n_sparse":58,"size":20121},"208352":{"edges":18,"n_sparse":15,"size":5558},"208383":{"edges":426,"n_sparse":269,"size":39031},"208399":{"edges":72,"n_sparse":48,"size":19985},"208400":{"edges":32,"n_sparse":26,"size":6048},"208401":{"edges":210,"n_sparse":171,"size":19694},"208411":{"edges":51,"n_sparse":51,"size":15399},"208437":{"edges":16,"n_sparse":12,"size":3423},"208447":{"edges":69,"n_sparse":58,"size":9597},"208462":{"edges":132,"n_sparse":125,"size":14022},"208464":{"edges":150,"n_sparse":120,"size":20019},"208470":{"edges":10,"n_sparse":10,"size":3316},"208471":{"edges":180,"n_sparse":76,"size":18757},"208510":{"edges":91,"n_sparse":84,"size":26599},"208524":{"edges":3276,"n_sparse":2909,"size":201827},"208551":{"edges":9,"n_sparse":9,"size":2990},"208552":{"edges":230,"n_sparse":230,"size":24980},"208558":{"edges":864,"n_sparse":814,"size":61633},"208564":{"edges":282,"n_sparse":245,"size":38838},"208573":{"edges":616,"n_sparse":616,"size":50011},"208603":{"edges":20,"n_sparse":20,"size":5868},"208610":{"edges":34,"n_sparse":32,"size":9598},"208611":{"edges":62,"n_sparse":61,"size":10689},"208612":{"edges":8,"n_sparse":4,"size":2592},"208623":{"edges":1011,"n_sparse":993,"size":138103},"208624":{"edges":1169,"n_sparse":1138,"size":104447},"208627":{"edges":21,"n_sparse":21,"size":6583},"208653":{"edges":4,"n_sparse":4,"size":1551},"208658":{"edges":990,"n_sparse":990,"size":81100},"208673":{"edges":154,"n_sparse":123,"size":13443},"208686":{"edges":115,"n_sparse":109,"size":12563},"208692":{"edges":350,"n_sparse":246,"size":36224},"208694":{"edges":11,"n_sparse":11,"size":3572},"208700":{"edges":25,"n_sparse":13,"size":7426},"208712":{"edges":30,"n_sparse":17,"size":5662},"208716":{"edges":36,"n_sparse":36,"size":5744},"208742":{"edges":87,"n_sparse":85,"size":12465},"208743":{"edges":117,"n_sparse":74,"size":16713},"208745":{"edges":54,"n_sparse":46,"size":7701},"208772":{"edges":120,"n_sparse":108,"size":20280},"208780":{"edges":5192,"n_sparse":5175,"size":320141},"208791":{"edges":4,"n_sparse":4,"size":1633},"208794":{"edges":18,"n_sparse":18,"size":5617},"208799":{"edges":11,"n_sparse":6,"size":3499},"208845":{"edges":4,"n_sparse":4,"size":1555},"208854":{"edges":38,"n_sparse":37,"size":9866},"208901":{"edges":8,"n_sparse":7,"size":2584},"208910":{"edges":24,"n_sparse":21,"size":4703},"208912":{"edges":38,"n_sparse":22,"size":7202},"208944":{"edges":1568,"n_sparse":1498,"size":136580},"208945":{"edges":12,"n_sparse":10,"size":3477},"208984":{"edges":30,"n_sparse":28,"size":8871},"209022":{"edges":146,"n_sparse":140,"size":40560},"209080":{"edges":4,"n_sparse":4,"size":1625},"209091":{"edges":228,"n_sparse":220,"size":30928},"209092":{"edges":294,"n_sparse":294,"size":28763},"209115":{"edges":230,"n_sparse":213,"size":23991},"209128":{"edges":40,"n_sparse":31,"size":12375},"209176":{"edges":7,"n_sparse":7,"size":2313},"209184":{"edges":501,"n_sparse":457,"size":63794},"209195":{"edges":216,"n_sparse":207,"size":37271},"209196":{"edges":22,"n_sparse":22,"size":4083},"209203":{"edges":64,"n_sparse":64,"size":17174},"209210":{"edges":3525,"n_sparse":3379,"size":213258},"209241":{"edges":744,"n_sparse":566,"size":85390},"209296":{"edges":26,"n_sparse":26,"size":7793},"209299":{"edges":73,"n_sparse":64,"size":21962},"209305":{"edges":22,"n_sparse":20,"size":6776},"209310":{"edges":106,"n_sparse":101,"size":30263},"209311":{"edges":73,"n_sparse":61,"size":20536},"209353":{"edges":17,"n_sparse":17,"size":4854},"209354":{"edges":42,"n_sparse":42,"size":12629},"209355":{"edges":20,"n_sparse":20,"size":6077},"209360":{"edges":1410,"n_sparse":1410,"size":101797},"209363":{"edges":612,"n_sparse":458,"size":71334},"209376":{"edges":78,"n_sparse":78,"size":14473},"209379":{"edges":13,"n_sparse":13,"size":4244},"209381":{"edges":38,"n_sparse":38,"size":10394},"209388":{"edges":22,"n_sparse":22,"size":6387},"209394":{"edges":162,"n_sparse":162,"size":28417},"209401":{"edges":222,"n_sparse":218,"size":21187},"209410":{"edges":1180,"n_sparse":894,"size":127070},"209445":{"edges":12,"n_sparse":9,"size":2369},"209449":{"edges":4,"n_sparse":4,"size":1323},"209471":{"edges":21,"n_sparse":21,"size":5934},"209472":{"edges":14,"n_sparse":14,"size":3011},"209478":{"edges":75,"n_sparse":75,"size":10937},"209482":{"edges":1840,"n_sparse":1753,"size":137993},"209483":{"edges":105,"n_sparse":97,"size":10533},"209500":{"edges":1235,"n_sparse":1092,"size":93695},"209501":{"edges":42,"n_sparse":23,"size":7753},"209510":{"edges":57,"n_sparse":57,"size":8311},"209511":{"edges":7,"n_sparse":7,"size":2477},"209521":{"edges":170,"n_sparse":170,"size":18402},"209531":{"edges":462,"n_sparse":315,"size":45406},"209575":{"edges":456,"n_sparse":425,"size":40460},"209589":{"edges":28,"n_sparse":20,"size":5268},"209606":{"edges":58,"n_sparse":56,"size":17087},"209627":{"edges":93,"n_sparse":93,"size":13582},"209637":{"edges":72,"n_sparse":72,"size":9091},"209661":{"edges":22,"n_sparse":19,"size":6733},"209776":{"edges":140,"n_sparse":140,"size":17570},"209803":{"edges":13,"n_sparse":12,"size":4103},"209805":{"edges":444,"n_sparse":424,"size":55625},"209806":{"edges":20,"n_sparse":19,"size":6177},"209816":{"edges":168,"n_sparse":164,"size":20164},"209817":{"edges":102,"n_sparse":100,"size":14382},"209819":{"edges":2516,"n_sparse":2422,"size":147285},"209830":{"edges":79,"n_sparse":75,"size":21212},"209862":{"edges":120,"n_sparse":90,"size":13539},"209863":{"edges":124,"n_sparse":78,"size":21377},"209884":{"edges":70,"n_sparse":70,"size":11724},"209899":{"edges":75,"n_sparse":68,"size":10665},"209905":{"edges":4,"n_sparse":4,"size":1488},"209935":{"edges":168,"n_sparse":168,"size":20052},"209936":{"edges":20,"n_sparse":13,"size":5954},"209963":{"edges":448,"n_sparse":448,"size":41737},"209964":{"edges":22,"n_sparse":22,"size":7054},"209988":{"edges":22,"n_sparse":22,"size":6833},"210045":{"edges":22,"n_sparse":22,"size":6675},"210132":{"edges":122,"n_sparse":104,"size":36246},"210134":{"edges":4,"n_sparse":3,"size":1489},"210136":{"edges":270,"n_sparse":266,"size":28179},"210192":{"edges":11,"n_sparse":9,"size":3452},"210238":{"edges":45,"n_sparse":43,"size":6431},"210251":{"edges":79,"n_sparse":59,"size":22084},"210259":{"edges":435,"n_sparse":388,"size":34377},"210282":{"edges":28,"n_sparse":28,"size":5576},"210296":{"edges":97,"n_sparse":81,"size":28425},"210303":{"edges":21,"n_sparse":19,"size":6124},"210308":{"edges":4,"n_sparse":4,"size":1513},"210326":{"edges":15,"n_sparse":9,"size":4793},"210331":{"edges":118,"n_sparse":86,"size":18213},"210361":{"edges":46,"n_sparse":42,"size":13758},"210365":{"edges":5697,"n_sparse":5544,"size":370005},"210450":{"edges":720,"n_sparse":690,"size":63042},"210455":{"edges":882,"n_sparse":864,"size":74074},"210491":{"edges":2754,"n_sparse":2729,"size":178235},"210493":{"edges":67,"n_sparse":61,"size":19427},"210496":{"edges":273,"n_sparse":218,"size":26178},"210498":{"edges":216,"n_sparse":189,"size":21903},"210526":{"edges":10,"n_sparse":9,"size":2954},"210557":{"edges":72,"n_sparse":72,"size":12827},"210563":{"edges":2698,"n_sparse":2379,"size":182308},"210565":{"edges":378,"n_sparse":325,"size":34690},"210566":{"edges":4,"n_sparse":4,"size":1500},"210583":{"edges":117,"n_sparse":108,"size":16147},"210589":{"edges":81,"n_sparse":81,"size":11562},"210595":{"edges":15,"n_sparse":12,"size":4783},"210598":{"edges":150,"n_sparse":88,"size":38496},"210607":{"edges":25,"n_sparse":24,"size":7618},"210655":{"edges":196,"n_sparse":172,"size":22833},"210656":{"edges":26,"n_sparse":26,"size":8105},"210660":{"edges":43,"n_sparse":42,"size":12849},"210730":{"edges":71,"n_sparse":67,"size":16694},"210793":{"edges":310,"n_sparse":202,"size":31825},"210797":{"edges":11,"n_sparse":11,"size":3635},"210806":{"edges":21,"n_sparse":21,"size":3878},"210807":{"edges":21,"n_sparse":21,"size":3779},"210833":{"edges":4,"n_sparse":3,"size":1255},"210850":{"edges":120,"n_sparse":100,"size":12563},"210854":{"edges":40,"n_sparse":38,"size":6932},"210861":{"edges":594,"n_sparse":540,"size":57243},"210868":{"edges":8,"n_sparse":8,"size":2156},"210872":{"edges":19,"n_sparse":17,"size":5729},"210874":{"edges":45,"n_sparse":43,"size":12903},"210875":{"edges":56,"n_sparse":43,"size":16559},"210884":{"edges":39,"n_sparse":37,"size":11812},"210895":{"edges":7,"n_sparse":7,"size":2343},"210910":{"edges":4,"n_sparse":3,"size":1523},"210913":{"edges":24,"n_sparse":19,"size":6851},"210922":{"edges":152,"n_sparse":93,"size":42535},"210923":{"edges":5,"n_sparse":4,"size":1834},"210933":{"edges":308,"n_sparse":282,"size":35456},"210942":{"edges":7,"n_sparse":7,"size":2414},"210951":{"edges":518,"n_sparse":473,"size":46757},"211039":{"edges":36,"n_sparse":35,"size":6804},"211109":{"edges":4,"n_sparse":4,"size":1508},"211150":{"edges":28,"n_sparse":28,"size":5187},"211155":{"edges":16,"n_sparse":14,"size":3295},"211172":{"edges":10,"n_sparse":10,"size":3219},"211192":{"edges":840,"n_sparse":821,"size":61982},"211215":{"edges":14,"n_sparse":14,"size":4460},"211225":{"edges":17,"n_sparse":17,"size":5230},"211230":{"edges":3396,"n_sparse":3243,"size":255183},"211243":{"edges":649,"n_sparse":649,"size":53138},"211280":{"edges":18,"n_sparse":16,"size":5501},"211281":{"edges":4,"n_sparse":3,"size":1399},"211288":{"edges":36,"n_sparse":36,"size":5977},"211321":{"edges":12,"n_sparse":12,"size":4069},"211340":{"edges":132,"n_sparse":99,"size":13330},"211349":{"edges":7,"n_sparse":6,"size":2317},"211358":{"edges":1008,"n_sparse":1006,"size":76906},"211367":{"edges":51,"n_sparse":19,"size":14708},"211371":{"edges":8,"n_sparse":7,"size":2679},"211379":{"edges":7,"n_sparse":7,"size":2305},"211415":{"edges":72,"n_sparse":71,"size":10338},"211527":{"edges":96,"n_sparse":57,"size":11667},"211580":{"edges":640,"n_sparse":604,"size":49718},"211616":{"edges":196,"n_sparse":196,"size":22578},"211617":{"edges":371,"n_sparse":371,"size":33931},"211635":{"edges":4,"n_sparse":4,"size":1561},"211651":{"edges":28,"n_sparse":28,"size":5555},"211675":{"edges":1611,"n_sparse":1605,"size":134675},"211710":{"edges":636,"n_sparse":596,"size":61373},"211723":{"edges":1048,"n_sparse":759,"size":86809},"211746":{"edges":336,"n_sparse":333,"size":45670},"211765":{"edges":210,"n_sparse":205,"size":22669},"211801":{"edges":14,"n_sparse":14,"size":4437},"211810":{"edges":55,"n_sparse":52,"size":16059},"211843":{"edges":4,"n_sparse":4,"size":1593},"211855":{"edges":14,"n_sparse":13,"size":4174},"211882":{"edges":14,"n_sparse":14,"size":4454},"211911":{"edges":16,"n_sparse":16,"size":5209},"211929":{"edges":8,"n_sparse":7,"size":2738},"211950":{"edges":13,"n_sparse":12,"size":4099},"211962":{"edges":15,"n_sparse":13,"size":4701},"211964":{"edges":42,"n_sparse":38,"size":7709},"211970":{"edges":8,"n_sparse":8,"size":2778},"211988":{"edges":326,"n_sparse":319,"size":53481},"211994":{"edges":7,"n_sparse":6,"size":2119},"211996":{"edges":11,"n_sparse":11,"size":3559},"212018":{"edges":682,"n_sparse":662,"size":55393},"212028":{"edges":23,"n_sparse":22,"size":7150},"212038":{"edges":52,"n_sparse":52,"size":16004},"212045":{"edges":28,"n_sparse":28,"size":8758},"212097":{"edges":8,"n_sparse":8,"size":2538},"212099":{"edges":15,"n_sparse":10,"size":4740},"212102":{"edges":2310,"n_sparse":2113,"size":173286},"212121":{"edges":13,"n_sparse":13,"size":3798},"212122":{"edges":51,"n_sparse":48,"size":15325},"212154":{"edges":7,"n_sparse":7,"size":2429},"212157":{"edges":39,"n_sparse":35,"size":11897},"212161":{"edges":8,"n_sparse":7,"size":2646},"212194":{"edges":190,"n_sparse":87,"size":52213},"212268":{"edges":12,"n_sparse":12,"size":3893},"212269":{"edges":34,"n_sparse":32,"size":9859},"212273":{"edges":3836,"n_sparse":3802,"size":242683},"212279":{"edges":15,"n_sparse":4,"size":4706},"212295":{"edges":68,"n_sparse":67,"size":20448},"212304":{"edges":36,"n_sparse":36,"size":10298},"212306":{"edges":156,"n_sparse":130,"size":21695},"212320":{"edges":33,"n_sparse":32,"size":9924},"212327":{"edges":56,"n_sparse":48,"size":10006},"212379":{"edges":46,"n_sparse":42,"size":14161},"212436":{"edges":4,"n_sparse":4,"size":1580},"212477":{"edges":102,"n_sparse":91,"size":27984},"212479":{"edges":20,"n_sparse":20,"size":3036},"212480":{"edges":73,"n_sparse":65,"size":20231},"212489":{"edges":558,"n_sparse":533,"size":40447},"212520":{"edges":52,"n_sparse":46,"size":15596},"212526":{"edges":8,"n_sparse":8,"size":1939},"212535":{"edges":78,"n_sparse":76,"size":13902},"212576":{"edges":104,"n_sparse":64,"size":11860},"212608":{"edges":108,"n_sparse":105,"size":15489},"212614":{"edges":2808,"n_sparse":2808,"size":211028},"212690":{"edges":1350,"n_sparse":1305,"size":106032},"212725":{"edges":212,"n_sparse":142,"size":25316},"212728":{"edges":16,"n_sparse":13,"size":3234},"212801":{"edges":10,"n_sparse":9,"size":3223},"212819":{"edges":21,"n_sparse":18,"size":3469},"212839":{"edges":9,"n_sparse":9,"size":2444},"212849":{"edges":16,"n_sparse":12,"size":5034},"212854":{"edges":12,"n_sparse":12,"size":2438},"212860":{"edges":5,"n_sparse":5,"size":1776},"212887":{"edges":14,"n_sparse":14,"size":2961},"212888":{"edges":134,"n_sparse":133,"size":21657},"212904":{"edges":54,"n_sparse":54,"size":9902},"212905":{"edges":57,"n_sparse":51,"size":8393},"212937":{"edges":64,"n_sparse":64,"size":8857},"212994":{"edges":8,"n_sparse":8,"size":2747},"213004":{"edges":78,"n_sparse":78,"size":10730},"213006":{"edges":32,"n_sparse":32,"size":9734},"213026":{"edges":270,"n_sparse":270,"size":35459},"213051":{"edges":47,"n_sparse":43,"size":12994},"213072":{"edges":12,"n_sparse":6,"size":3803},"213135":{"edges":20,"n_sparse":12,"size":5365},"213137":{"edges":132,"n_sparse":126,"size":13474},"213138":{"edges":11,"n_sparse":9,"size":3587},"213150":{"edges":1,"n_sparse":0,"size":755},"213176":{"edges":194,"n_sparse":156,"size":34002},"213189":{"edges":18,"n_sparse":15,"size":5291},"213217":{"edges":1275,"n_sparse":1194,"size":92247},"213224":{"edges":63,"n_sparse":39,"size":8666},"213227":{"edges":14,"n_sparse":14,"size":4486},"213246":{"edges":527,"n_sparse":500,"size":36974},"213260":{"edges":24,"n_sparse":22,"size":4020},"213312":{"edges":90,"n_sparse":87,"size":10808},"213378":{"edges":945,"n_sparse":945,"size":77823},"213388":{"edges":108,"n_sparse":103,"size":19383},"213407":{"edges":34,"n_sparse":34,"size":9916},"213411":{"edges":82,"n_sparse":80,"size":14792},"213426":{"edges":21,"n_sparse":21,"size":6000},"213433":{"edges":82,"n_sparse":82,"size":14829},"213436":{"edges":12,"n_sparse":12,"size":3905},"213491":{"edges":131,"n_sparse":119,"size":35340},"213498":{"edges":152,"n_sparse":146,"size":18955},"213535":{"edges":36,"n_sparse":35,"size":10646},"213586":{"edges":32,"n_sparse":20,"size":9661},"213591":{"edges":14,"n_sparse":14,"size":4519},"213593":{"edges":34,"n_sparse":26,"size":6213},"213645":{"edges":8,"n_sparse":8,"size":2612},"213674":{"edges":96,"n_sparse":94,"size":11910},"213690":{"edges":40,"n_sparse":36,"size":11735},"213702":{"edges":7,"n_sparse":6,"size":2522},"213716":{"edges":32,"n_sparse":22,"size":9359},"213721":{"edges":280,"n_sparse":276,"size":32782},"213736":{"edges":216,"n_sparse":216,"size":20950},"213756":{"edges":4,"n_sparse":3,"size":1560},"213801":{"edges":5,"n_sparse":5,"size":1885},"213871":{"edges":4,"n_sparse":4,"size":1590},"213872":{"edges":4,"n_sparse":4,"size":1498},"213876":{"edges":18,"n_sparse":16,"size":5470},"213895":{"edges":15,"n_sparse":13,"size":4686},"213931":{"edges":28,"n_sparse":28,"size":4809},"213953":{"edges":8,"n_sparse":8,"size":2580},"213969":{"edges":12,"n_sparse":12,"size":3842},"213972":{"edges":28,"n_sparse":28,"size":8489},"213973":{"edges":2329,"n_sparse":2126,"size":165433},"213976":{"edges":39,"n_sparse":38,"size":11838},"213978":{"edges":65,"n_sparse":48,"size":19219},"213994":{"edges":5,"n_sparse":5,"size":1687},"214012":{"edges":306,"n_sparse":292,"size":51147},"214018":{"edges":4,"n_sparse":4,"size":1461},"214028":{"edges":144,"n_sparse":120,"size":18362},"214032":{"edges":8,"n_sparse":8,"size":2576},"214044":{"edges":8,"n_sparse":8,"size":2534},"214070":{"edges":5,"n_sparse":5,"size":1733},"214094":{"edges":74,"n_sparse":68,"size":13707},"214096":{"edges":40,"n_sparse":38,"size":7484},"214103":{"edges":106,"n_sparse":27,"size":30443},"214120":{"edges":8,"n_sparse":8,"size":2878},"214133":{"edges":195,"n_sparse":191,"size":24893},"214154":{"edges":4,"n_sparse":4,"size":1469},"214155":{"edges":11,"n_sparse":11,"size":3610},"214187":{"edges":100,"n_sparse":89,"size":28231},"214200":{"edges":534,"n_sparse":534,"size":50144},"214231":{"edges":4,"n_sparse":4,"size":1515},"214273":{"edges":4,"n_sparse":4,"size":1445},"214275":{"edges":81,"n_sparse":78,"size":11220},"214313":{"edges":8,"n_sparse":4,"size":2550},"214324":{"edges":16,"n_sparse":16,"size":3422},"214373":{"edges":19,"n_sparse":18,"size":5866},"214377":{"edges":31,"n_sparse":31,"size":9240},"214383":{"edges":21,"n_sparse":21,"size":6195},"214410":{"edges":40,"n_sparse":38,"size":6932},"214439":{"edges":174,"n_sparse":166,"size":24316},"214460":{"edges":4,"n_sparse":3,"size":1452},"214461":{"edges":18,"n_sparse":15,"size":5643},"214487":{"edges":7,"n_sparse":6,"size":2469},"214510":{"edges":57,"n_sparse":54,"size":7579},"214511":{"edges":28,"n_sparse":28,"size":8570},"214517":{"edges":1256,"n_sparse":1187,"size":106217},"214518":{"edges":18,"n_sparse":18,"size":5686},"214520":{"edges":23,"n_sparse":23,"size":6771},"214522":{"edges":39,"n_sparse":39,"size":11831},"214621":{"edges":222,"n_sparse":168,"size":30880},"214628":{"edges":18,"n_sparse":18,"size":5431},"214662":{"edges":184,"n_sparse":167,"size":22241},"214665":{"edges":21,"n_sparse":19,"size":6563},"214679":{"edges":24,"n_sparse":24,"size":4173},"214697":{"edges":78,"n_sparse":78,"size":23365},"214755":{"edges":1474,"n_sparse":1398,"size":114306},"214783":{"edges":116,"n_sparse":93,"size":14469},"214787":{"edges":900,"n_sparse":782,"size":66558},"214793":{"edges":35,"n_sparse":14,"size":9586},"214801":{"edges":4,"n_sparse":3,"size":1454},"214826":{"edges":4,"n_sparse":4,"size":1461},"214835":{"edges":404,"n_sparse":404,"size":47221},"214846":{"edges":54,"n_sparse":52,"size":9986},"214860":{"edges":7,"n_sparse":7,"size":2426},"214869":{"edges":132,"n_sparse":132,"size":16202},"214876":{"edges":69,"n_sparse":58,"size":9562},"214900":{"edges":48,"n_sparse":44,"size":8683},"214902":{"edges":52,"n_sparse":47,"size":9316},"214907":{"edges":28,"n_sparse":28,"size":8612},"214916":{"edges":60,"n_sparse":55,"size":18393},"214927":{"edges":12,"n_sparse":12,"size":3879},"214938":{"edges":122,"n_sparse":97,"size":21409},"214952":{"edges":52,"n_sparse":52,"size":15707},"214958":{"edges":86,"n_sparse":86,"size":21563},"214962":{"edges":8,"n_sparse":8,"size":1936},"214965":{"edges":7,"n_sparse":4,"size":2347},"214985":{"edges":21,"n_sparse":20,"size":6388},"214998":{"edges":4,"n_sparse":4,"size":1547},"215014":{"edges":372,"n_sparse":233,"size":36128},"215064":{"edges":18,"n_sparse":18,"size":5681},"215092":{"edges":70,"n_sparse":70,"size":19914},"215110":{"edges":64,"n_sparse":64,"size":19048},"215168":{"edges":85,"n_sparse":54,"size":21460},"215192":{"edges":60,"n_sparse":57,"size":16878},"215206":{"edges":60,"n_sparse":56,"size":10601},"215211":{"edges":40,"n_sparse":24,"size":12323},"215239":{"edges":31,"n_sparse":31,"size":9401},"215256":{"edges":70,"n_sparse":50,"size":12231},"215272":{"edges":18,"n_sparse":18,"size":5642},"215309":{"edges":685,"n_sparse":665,"size":71337},"215310":{"edges":7,"n_sparse":7,"size":2493},"215320":{"edges":36,"n_sparse":36,"size":6814},"215331":{"edges":28,"n_sparse":15,"size":5349},"215352":{"edges":19,"n_sparse":19,"size":5790},"215358":{"edges":4,"n_sparse":3,"size":1490},"215383":{"edges":78,"n_sparse":72,"size":14035},"215390":{"edges":600,"n_sparse":583,"size":52350},"215401":{"edges":4,"n_sparse":4,"size":1531},"215422":{"edges":96,"n_sparse":58,"size":12164},"215429":{"edges":4,"n_sparse":3,"size":1398},"215430":{"edges":2262,"n_sparse":2262,"size":306524},"215446":{"edges":6,"n_sparse":4,"size":2011},"215457":{"edges":28,"n_sparse":28,"size":5388},"215498":{"edges":164,"n_sparse":164,"size":20215},"215515":{"edges":130,"n_sparse":87,"size":35502},"215559":{"edges":165,"n_sparse":165,"size":23299},"215596":{"edges":10,"n_sparse":10,"size":3482},"215602":{"edges":4,"n_sparse":4,"size":1496},"215650":{"edges":4,"n_sparse":4,"size":1531},"215727":{"edges":783,"n_sparse":714,"size":65365},"215760":{"edges":7,"n_sparse":7,"size":2407},"215814":{"edges":900,"n_sparse":896,"size":101106},"215830":{"edges":7,"n_sparse":7,"size":2334},"215833":{"edges":30,"n_sparse":29,"size":9252},"215841":{"edges":18,"n_sparse":16,"size":3684},"215842":{"edges":55,"n_sparse":54,"size":14399},"215866":{"edges":7,"n_sparse":6,"size":2110},"215875":{"edges":9,"n_sparse":9,"size":2818},"215887":{"edges":20,"n_sparse":20,"size":6229},"215888":{"edges":14,"n_sparse":5,"size":4466},"215904":{"edges":56,"n_sparse":56,"size":10424},"215910":{"edges":13,"n_sparse":13,"size":3881},"215935":{"edges":69,"n_sparse":61,"size":9426},"215973":{"edges":33,"n_sparse":32,"size":10001},"215974":{"edges":33,"n_sparse":32,"size":10001},"215985":{"edges":168,"n_sparse":165,"size":20230},"216023":{"edges":46,"n_sparse":44,"size":8481},"216059":{"edges":68,"n_sparse":68,"size":12282},"216099":{"edges":150,"n_sparse":150,"size":13769},"216117":{"edges":43,"n_sparse":34,"size":12611},"216157":{"edges":132,"n_sparse":126,"size":13474},"216158":{"edges":46,"n_sparse":23,"size":13639},"216165":{"edges":22,"n_sparse":20,"size":4473},"216185":{"edges":42,"n_sparse":42,"size":7522},"216190":{"edges":7,"n_sparse":6,"size":2174},"216196":{"edges":268,"n_sparse":267,"size":31977},"216203":{"edges":50,"n_sparse":50,"size":13623},"216227":{"edges":4,"n_sparse":4,"size":1446},"216285":{"edges":51,"n_sparse":19,"size":14709},"216340":{"edges":14,"n_sparse":14,"size":3206},"216352":{"edges":54,"n_sparse":54,"size":9813},"216354":{"edges":92,"n_sparse":65,"size":15972},"216386":{"edges":4,"n_sparse":4,"size":1452},"216387":{"edges":375,"n_sparse":346,"size":30048},"216403":{"edges":8,"n_sparse":8,"size":1897},"216457":{"edges":108,"n_sparse":97,"size":14668},"216472":{"edges":4,"n_sparse":4,"size":1317},"216482":{"edges":8,"n_sparse":0,"size":2498},"216490":{"edges":9,"n_sparse":8,"size":3021},"216540":{"edges":70,"n_sparse":68,"size":19512},"216578":{"edges":42,"n_sparse":32,"size":7761},"216579":{"edges":9,"n_sparse":9,"size":2889},"216632":{"edges":24,"n_sparse":24,"size":7609},"216660":{"edges":12,"n_sparse":11,"size":3730},"216675":{"edges":29,"n_sparse":27,"size":8903},"216718":{"edges":60,"n_sparse":48,"size":7885},"216774":{"edges":12,"n_sparse":9,"size":2408},"216793":{"edges":49,"n_sparse":48,"size":14352},"216834":{"edges":20,"n_sparse":19,"size":6113},"216873":{"edges":52,"n_sparse":39,"size":8351},"216951":{"edges":82,"n_sparse":78,"size":14002},"216956":{"edges":164,"n_sparse":163,"size":19906},"216962":{"edges":8,"n_sparse":6,"size":2620},"216974":{"edges":12,"n_sparse":9,"size":3971},"216993":{"edges":63,"n_sparse":60,"size":18999},"217003":{"edges":1386,"n_sparse":1340,"size":108451},"217006":{"edges":140,"n_sparse":106,"size":16137},"217026":{"edges":8,"n_sparse":7,"size":2662},"217064":{"edges":4,"n_sparse":4,"size":1453},"217171":{"edges":330,"n_sparse":178,"size":32748},"217186":{"edges":336,"n_sparse":221,"size":38650},"217188":{"edges":8,"n_sparse":7,"size":2863},"217225":{"edges":30,"n_sparse":25,"size":9358},"217242":{"edges":49,"n_sparse":42,"size":14749},"217347":{"edges":121,"n_sparse":101,"size":34543},"217369":{"edges":30,"n_sparse":17,"size":8996},"217388":{"edges":37,"n_sparse":36,"size":8809},"217389":{"edges":8,"n_sparse":7,"size":2708},"217415":{"edges":5,"n_sparse":5,"size":1722},"217417":{"edges":60,"n_sparse":59,"size":16565},"217424":{"edges":976,"n_sparse":943,"size":70151},"217439":{"edges":28,"n_sparse":28,"size":5525},"217469":{"edges":66,"n_sparse":57,"size":9295},"217470":{"edges":4,"n_sparse":3,"size":1344},"217513":{"edges":26,"n_sparse":22,"size":7977},"217514":{"edges":26,"n_sparse":24,"size":7978},"217564":{"edges":27,"n_sparse":24,"size":8216},"217581":{"edges":12,"n_sparse":12,"size":2520},"217603":{"edges":56,"n_sparse":56,"size":16529},"217604":{"edges":7,"n_sparse":6,"size":2351},"217639":{"edges":74,"n_sparse":70,"size":13685},"217645":{"edges":4,"n_sparse":4,"size":1561},"217660":{"edges":2465,"n_sparse":2435,"size":174967},"217677":{"edges":105,"n_sparse":99,"size":31426},"217686":{"edges":102,"n_sparse":102,"size":14772},"217722":{"edges":13,"n_sparse":13,"size":4020},"217729":{"edges":44,"n_sparse":44,"size":6245},"217779":{"edges":33,"n_sparse":11,"size":10200},"217785":{"edges":49,"n_sparse":47,"size":14792},"217806":{"edges":10,"n_sparse":10,"size":3361},"217836":{"edges":34,"n_sparse":23,"size":10296},"217865":{"edges":12,"n_sparse":12,"size":3731},"217899":{"edges":25,"n_sparse":23,"size":7701},"217900":{"edges":27,"n_sparse":21,"size":8192},"218037":{"edges":26,"n_sparse":25,"size":7294},"218139":{"edges":14,"n_sparse":14,"size":2821},"218158":{"edges":4,"n_sparse":4,"size":1416},"218160":{"edges":80,"n_sparse":79,"size":10520},"218197":{"edges":43,"n_sparse":42,"size":12681},"218213":{"edges":16,"n_sparse":16,"size":3273},"218276":{"edges":24,"n_sparse":24,"size":4746},"218347":{"edges":8,"n_sparse":6,"size":2039},"218390":{"edges":744,"n_sparse":566,"size":85316},"218424":{"edges":21,"n_sparse":21,"size":6253},"218490":{"edges":76,"n_sparse":74,"size":12721},"218549":{"edges":8,"n_sparse":7,"size":2686},"218590":{"edges":7,"n_sparse":7,"size":2300},"218591":{"edges":22,"n_sparse":21,"size":4148},"218709":{"edges":11,"n_sparse":11,"size":3628},"218711":{"edges":40,"n_sparse":30,"size":4820},"218784":{"edges":28,"n_sparse":27,"size":5515},"218860":{"edges":44,"n_sparse":44,"size":8332},"218944":{"edges":10,"n_sparse":10,"size":3097},"219008":{"edges":22,"n_sparse":22,"size":7025},"219015":{"edges":15,"n_sparse":12,"size":4754},"219016":{"edges":7,"n_sparse":7,"size":2511},"219249":{"edges":12,"n_sparse":11,"size":4051}}